Workbook

Sheet Task Map
A1: Assigned | B1: Project | C1: Stage | D1: Task | E1: Description | F1: Agent | G1: Skill | H1: Document | I1: Integrations | J1: Task Slug | K1: Scope
A2: Owner | B2: Project Type | C2: Stage / Pseudo-stage | D2: Task | E2: Description | F2: Agent | G2: Linked skill | H2: Linked document reference | I2: MCP / app / platform surfaces | J2: Task slug | K2: Project scope
B3: Deal Pipeline | C3: Setup | D3: Project Source Choice | E3: Choose the source of truth or setup route for the project. | F3: =HYPERLINK('Link Config'!$B$2&"plugins/vc/agents/vc-deal-room-setup-guide.md","Deal Pipeline Setup Guide") | G3: None declared | H3: None declared | I3: None declared | J3: project-source-choice | K3: setup
B4: Deal Pipeline | C4: Setup | D4: Project Variable Review | E4: Review workspace and project variables before normal execution. | F4: =HYPERLINK('Link Config'!$B$2&"plugins/vc/agents/vc-deal-room-setup-guide.md","Deal Pipeline Setup Guide") | G4: None declared | H4: None declared | I4: None declared | J4: project-variable-review | K4: setup
B5: Deal Pipeline | C5: Setup | D5: Project Schedule Review | E5: Review optional schedule groups before enabling recurring work. | F5: =HYPERLINK('Link Config'!$B$2&"plugins/vc/agents/vc-deal-room-setup-guide.md","Deal Pipeline Setup Guide") | G5: None declared | H5: None declared | I5: None declared | J5: project-schedule-review | K5: setup
B6: Deal Pipeline | C6: Setup | D6: Project Team Invite Review | E6: Review suggested collaborators before sending invitations. | F6: =HYPERLINK('Link Config'!$B$2&"plugins/vc/agents/vc-deal-room-setup-guide.md","Deal Pipeline Setup Guide") | G6: None declared | H6: None declared | I6: None declared | J6: project-team-invite | K6: setup
A7: Alex | B7: Deal Pipeline | C7: Setup | D7: =HYPERLINK('Link Config'!$B$2&"plugins/vc/tasks/screen-inbound-opportunity.md","Capture Opportunity Intake") | E7: Capture source context, known fields, missing information, and guided project-creation values for one venture-capital opportunity before formal screening. | F7: =HYPERLINK('Link Config'!$B$2&"plugins/vc/agents/vc-dealflow-concierge.md","Dealflow Concierge") | G7: =HYPERLINK('Link Config'!$B$2&"plugins/vc/skills/deal-room-setup-and-source-ingestion/SKILL.md","Deal Pipeline Setup & Source Ingestion") | H7: =HYPERLINK('Link Config'!$B$2&"plugins/vc/alludium/documents/deal-room/deal-room-sop.md","Deal Pipeline Operating SOP (operating_guidance)") | I7: alludium-platform harmonic-mcp-oauth affinity-mcp-server exa-mcp-hosted brave-search-mcp serpapi-mcp firecrawl-mcp-hosted dealroom-mcp google_drive | J7: screen-inbound-opportunity | K7: setup
A8: Alex | B8: Deal Pipeline | C8: Setup | D8: =HYPERLINK('Link Config'!$B$2&"plugins/vc/tasks/screen-inbound-opportunity.md","Capture Opportunity Intake") | E8: Capture source context, known fields, missing information, and guided project-creation values for one venture-capital opportunity before formal screening. | F8: =HYPERLINK('Link Config'!$B$2&"plugins/vc/agents/vc-dealflow-concierge.md","Dealflow Concierge") | G8: =HYPERLINK('Link Config'!$B$2&"plugins/vc/skills/company-research-and-enrichment/SKILL.md","Company Research & Enrichment") | H8: =HYPERLINK('Link Config'!$B$2&"plugins/vc/alludium/documents/shared/evidence-citation-style-guide.md","Evidence And Citation Style Guide (style_guide)") | I8: alludium-platform harmonic-mcp-oauth affinity-mcp-server exa-mcp-hosted brave-search-mcp serpapi-mcp firecrawl-mcp-hosted dealroom-mcp google_drive | J8: screen-inbound-opportunity | K8: setup
A9: Alex | B9: Deal Pipeline | C9: Setup | D9: =HYPERLINK('Link Config'!$B$2&"plugins/vc/tasks/screen-inbound-opportunity.md","Capture Opportunity Intake") | E9: Capture source context, known fields, missing information, and guided project-creation values for one venture-capital opportunity before formal screening. | F9: =HYPERLINK('Link Config'!$B$2&"plugins/vc/agents/vc-dealflow-concierge.md","Dealflow Concierge") | G9: =HYPERLINK('Link Config'!$B$2&"plugins/vc/skills/citation-enforcement/SKILL.md","Citation Enforcement") | H9: =HYPERLINK('Link Config'!$B$2&"plugins/vc/alludium/documents/shared/template-use-guidance.md","Template Use Guidance (operating_guidance)") | I9: alludium-platform harmonic-mcp-oauth affinity-mcp-server exa-mcp-hosted brave-search-mcp serpapi-mcp firecrawl-mcp-hosted dealroom-mcp google_drive | J9: screen-inbound-opportunity | K9: setup
A10: Alex | B10: Deal Pipeline | C10: Setup | D10: =HYPERLINK('Link Config'!$B$2&"plugins/vc/tasks/screen-inbound-opportunity.md","Capture Opportunity Intake") | E10: Capture source context, known fields, missing information, and guided project-creation values for one venture-capital opportunity before formal screening. | F10: =HYPERLINK('Link Config'!$B$2&"plugins/vc/agents/vc-dealflow-concierge.md","Dealflow Concierge") | G10: =HYPERLINK('Link Config'!$B$2&"plugins/vc/skills/pitch-deck-explainer/SKILL.md","Pitch Deck Explainer") | I10: alludium-platform harmonic-mcp-oauth affinity-mcp-server exa-mcp-hosted brave-search-mcp serpapi-mcp firecrawl-mcp-hosted dealroom-mcp google_drive | J10: screen-inbound-opportunity | K10: setup
B11: Deal Pipeline | C11: Setup | D11: Project Source Setup | E11: Review selected source route and setup intent before writes or imports. | F11: =HYPERLINK('Link Config'!$B$2&"plugins/vc/agents/vc-deal-room-setup-guide.md","Deal Pipeline Setup Guide") | G11: None declared | H11: None declared | I11: None declared | J11: project-source-setup | K11: setup
B12: Deal Pipeline | C12: Setup | D12: =HYPERLINK('Link Config'!$B$2&"plugins/vc/tasks/vc-pack-variable-discovery.md","VC Pack Variable Discovery") | E12: Best-effort, review-only discovery for VC Pack Setup variables and invite suggestions. | F12: =HYPERLINK('Link Config'!$B$2&"plugins/vc/agents/vc-deal-room-setup-guide.md","Deal Pipeline Setup Guide") | G12: None declared | H12: None declared | I12: alludium-platform affinity-mcp-server | J12: vc-pack-variable-discovery | K12: setup
B13: Deal Pipeline | C13: Setup | D13: =HYPERLINK('Link Config'!$B$2&"plugins/vc/tasks/affinity-setup.md","Set Up Affinity for Deal Pipelines") | E13: Coordinate Affinity connection readiness, list discovery, read-preview policy, and optional write-back proposal scope for Deal Pipeline setup. | F13: =HYPERLINK('Link Config'!$B$2&"plugins/vc/agents/vc-integration-operator.md","Integration Operator") | G13: =HYPERLINK('Link Config'!$B$2&"plugins/vc/skills/vc-affinity-discovery/SKILL.md","VC Affinity Discovery") | H13: None declared | I13: affinity-mcp-server | J13: affinity-setup | K13: setup
B14: Deal Pipeline | C14: Setup | D14: =HYPERLINK('Link Config'!$B$2&"plugins/vc/tasks/affinity-setup.md","Set Up Affinity for Deal Pipelines") | E14: Coordinate Affinity connection readiness, list discovery, read-preview policy, and optional write-back proposal scope for Deal Pipeline setup. | F14: =HYPERLINK('Link Config'!$B$2&"plugins/vc/agents/vc-integration-operator.md","Integration Operator") | G14: =HYPERLINK('Link Config'!$B$2&"plugins/vc/skills/vc-affinity-sync-read/SKILL.md","VC Affinity Sync Read") | I14: affinity-mcp-server | J14: affinity-setup | K14: setup
B15: Deal Pipeline | C15: Setup | D15: =HYPERLINK('Link Config'!$B$2&"plugins/vc/tasks/affinity-setup.md","Set Up Affinity for Deal Pipelines") | E15: Coordinate Affinity connection readiness, list discovery, read-preview policy, and optional write-back proposal scope for Deal Pipeline setup. | F15: =HYPERLINK('Link Config'!$B$2&"plugins/vc/agents/vc-integration-operator.md","Integration Operator") | G15: =HYPERLINK('Link Config'!$B$2&"plugins/vc/skills/vc-affinity-sync-write/SKILL.md","VC Affinity Sync Write") | I15: affinity-mcp-server | J15: affinity-setup | K15: setup
B16: Deal Pipeline | C16: Setup | D16: =HYPERLINK('Link Config'!$B$2&"plugins/vc/tasks/affinity-setup.md","Set Up Affinity for Deal Pipelines") | E16: Coordinate Affinity connection readiness, list discovery, read-preview policy, and optional write-back proposal scope for Deal Pipeline setup. | F16: =HYPERLINK('Link Config'!$B$2&"plugins/vc/agents/vc-integration-operator.md","Integration Operator") | G16: =HYPERLINK('Link Config'!$B$2&"plugins/vc/skills/citation-enforcement/SKILL.md","Citation Enforcement") | I16: affinity-mcp-server | J16: affinity-setup | K16: setup
B17: Deal Pipeline | C17: Setup | D17: =HYPERLINK('Link Config'!$B$2&"plugins/vc/tasks/affinity-deal-room-import.md","Import Affinity Deal Pipeline Seed") | E17: Import one approved Affinity seed deal into an already-created Deal Pipeline project with source provenance and approval evidence. | F17: =HYPERLINK('Link Config'!$B$2&"plugins/vc/agents/vc-deal-room-setup-guide.md","Deal Pipeline Setup Guide") | G17: =HYPERLINK('Link Config'!$B$2&"plugins/vc/skills/vc-affinity-deal-room-import/SKILL.md","VC Affinity Deal Pipeline Import") | H17: None declared | I17: affinity-mcp-server alludium-platform | J17: affinity-deal-room-import | K17: setup
B18: Deal Pipeline | C18: Setup | D18: =HYPERLINK('Link Config'!$B$2&"plugins/vc/tasks/affinity-deal-room-import.md","Import Affinity Deal Pipeline Seed") | E18: Import one approved Affinity seed deal into an already-created Deal Pipeline project with source provenance and approval evidence. | F18: =HYPERLINK('Link Config'!$B$2&"plugins/vc/agents/vc-deal-room-setup-guide.md","Deal Pipeline Setup Guide") | G18: =HYPERLINK('Link Config'!$B$2&"plugins/vc/skills/vc-affinity-sync-read/SKILL.md","VC Affinity Sync Read") | I18: affinity-mcp-server alludium-platform | J18: affinity-deal-room-import | K18: setup
B19: Deal Pipeline | C19: Setup | D19: =HYPERLINK('Link Config'!$B$2&"plugins/vc/tasks/affinity-deal-room-import.md","Import Affinity Deal Pipeline Seed") | E19: Import one approved Affinity seed deal into an already-created Deal Pipeline project with source provenance and approval evidence. | F19: =HYPERLINK('Link Config'!$B$2&"plugins/vc/agents/vc-deal-room-setup-guide.md","Deal Pipeline Setup Guide") | G19: =HYPERLINK('Link Config'!$B$2&"plugins/vc/skills/deal-room-setup-and-source-ingestion/SKILL.md","Deal Pipeline Setup & Source Ingestion") | I19: affinity-mcp-server alludium-platform | J19: affinity-deal-room-import | K19: setup
B20: Deal Pipeline | C20: Setup | D20: =HYPERLINK('Link Config'!$B$2&"plugins/vc/tasks/affinity-deal-room-import.md","Import Affinity Deal Pipeline Seed") | E20: Import one approved Affinity seed deal into an already-created Deal Pipeline project with source provenance and approval evidence. | F20: =HYPERLINK('Link Config'!$B$2&"plugins/vc/agents/vc-deal-room-setup-guide.md","Deal Pipeline Setup Guide") | G20: =HYPERLINK('Link Config'!$B$2&"plugins/vc/skills/citation-enforcement/SKILL.md","Citation Enforcement") | I20: affinity-mcp-server alludium-platform | J20: affinity-deal-room-import | K20: setup
B21: Deal Pipeline | C21: General | D21: =HYPERLINK('Link Config'!$B$2&"plugins/vc/tasks/prepare-initial-call.md","Prepare Meeting") | E21: Prepare a founder, management, advisor, customer, expert, partner, IC, legal, or closing meeting for one venture-capital opportunity with evidence capture, human review gates, and next-action recommendations. | F21: =HYPERLINK('Link Config'!$B$2&"plugins/vc/agents/vc-meeting-operator.md","Meeting Operator") | G21: =HYPERLINK('Link Config'!$B$2&"plugins/vc/skills/meeting-prep-and-summary/SKILL.md","Meeting Prep & Summary") | H21: =HYPERLINK('Link Config'!$B$2&"plugins/vc/alludium/documents/deal-room/initial-call-brief-template.md","Initial Call Brief Template (output_template, to initial_call_brief_artifact_id)") | I21: alludium-platform harmonic-mcp-oauth affinity-mcp-server exa-mcp-hosted brave-search-mcp serpapi-mcp firecrawl-mcp-hosted dealroom-mcp granola-mcp google_drive | J21: prepare-initial-call | K21: general
B22: Deal Pipeline | C22: General | D22: =HYPERLINK('Link Config'!$B$2&"plugins/vc/tasks/prepare-initial-call.md","Prepare Meeting") | E22: Prepare a founder, management, advisor, customer, expert, partner, IC, legal, or closing meeting for one venture-capital opportunity with evidence capture, human review gates, and next-action recommendations. | F22: =HYPERLINK('Link Config'!$B$2&"plugins/vc/agents/vc-meeting-operator.md","Meeting Operator") | G22: =HYPERLINK('Link Config'!$B$2&"plugins/vc/skills/company-research-and-enrichment/SKILL.md","Company Research & Enrichment") | H22: =HYPERLINK('Link Config'!$B$2&"plugins/vc/alludium/documents/shared/evidence-citation-style-guide.md","Evidence And Citation Style Guide (style_guide)") | I22: alludium-platform harmonic-mcp-oauth affinity-mcp-server exa-mcp-hosted brave-search-mcp serpapi-mcp firecrawl-mcp-hosted dealroom-mcp granola-mcp google_drive | J22: prepare-initial-call | K22: general
B23: Deal Pipeline | C23: General | D23: =HYPERLINK('Link Config'!$B$2&"plugins/vc/tasks/prepare-initial-call.md","Prepare Meeting") | E23: Prepare a founder, management, advisor, customer, expert, partner, IC, legal, or closing meeting for one venture-capital opportunity with evidence capture, human review gates, and next-action recommendations. | F23: =HYPERLINK('Link Config'!$B$2&"plugins/vc/agents/vc-meeting-operator.md","Meeting Operator") | G23: =HYPERLINK('Link Config'!$B$2&"plugins/vc/skills/citation-enforcement/SKILL.md","Citation Enforcement") | H23: =HYPERLINK('Link Config'!$B$2&"plugins/vc/alludium/documents/shared/template-use-guidance.md","Template Use Guidance (operating_guidance)") | I23: alludium-platform harmonic-mcp-oauth affinity-mcp-server exa-mcp-hosted brave-search-mcp serpapi-mcp firecrawl-mcp-hosted dealroom-mcp granola-mcp google_drive | J23: prepare-initial-call | K23: general
B24: Deal Pipeline | C24: General | D24: =HYPERLINK('Link Config'!$B$2&"plugins/vc/tasks/prepare-initial-call.md","Prepare Meeting") | E24: Prepare a founder, management, advisor, customer, expert, partner, IC, legal, or closing meeting for one venture-capital opportunity with evidence capture, human review gates, and next-action recommendations. | F24: =HYPERLINK('Link Config'!$B$2&"plugins/vc/agents/vc-meeting-operator.md","Meeting Operator") | G24: =HYPERLINK('Link Config'!$B$2&"plugins/vc/skills/pitch-deck-explainer/SKILL.md","Pitch Deck Explainer") | I24: alludium-platform harmonic-mcp-oauth affinity-mcp-server exa-mcp-hosted brave-search-mcp serpapi-mcp firecrawl-mcp-hosted dealroom-mcp granola-mcp google_drive | J24: prepare-initial-call | K24: general
A25: Alex | B25: Deal Pipeline | C25: General | D25: =HYPERLINK('Link Config'!$B$2&"plugins/vc/tasks/request-founder-materials.md","Request Founder Materials") | E25: Request Founder Materials for one venture-capital opportunity with evidence capture, human review gates, and next-action recommendations. | F25: =HYPERLINK('Link Config'!$B$2&"plugins/vc/agents/vc-dealflow-concierge.md","Dealflow Concierge") | G25: =HYPERLINK('Link Config'!$B$2&"plugins/vc/skills/citation-enforcement/SKILL.md","Citation Enforcement") | H25: =HYPERLINK('Link Config'!$B$2&"plugins/vc/alludium/documents/deal-room/founder-materials-request-template.md","Founder Materials Request Template (output_template, to founder_materials_request_artifact_id)") | I25: alludium-platform harmonic-mcp-oauth affinity-mcp-server exa-mcp-hosted brave-search-mcp serpapi-mcp firecrawl-mcp-hosted dealroom-mcp google_drive | J25: request-founder-materials | K25: general
A26: Alex | B26: Deal Pipeline | C26: General | D26: =HYPERLINK('Link Config'!$B$2&"plugins/vc/tasks/request-founder-materials.md","Request Founder Materials") | E26: Request Founder Materials for one venture-capital opportunity with evidence capture, human review gates, and next-action recommendations. | F26: =HYPERLINK('Link Config'!$B$2&"plugins/vc/agents/vc-dealflow-concierge.md","Dealflow Concierge") | G26: =HYPERLINK('Link Config'!$B$2&"plugins/vc/skills/founder-materials-request/SKILL.md","Founder Materials Request") | H26: =HYPERLINK('Link Config'!$B$2&"plugins/vc/alludium/documents/shared/file-naming-source-index-sop.md","File Naming And Source Index SOP (operating_guidance)") | I26: alludium-platform harmonic-mcp-oauth affinity-mcp-server exa-mcp-hosted brave-search-mcp serpapi-mcp firecrawl-mcp-hosted dealroom-mcp google_drive | J26: request-founder-materials | K26: general
A27: Alex | B27: Deal Pipeline | C27: General | D27: =HYPERLINK('Link Config'!$B$2&"plugins/vc/tasks/request-founder-materials.md","Request Founder Materials") | E27: Request Founder Materials for one venture-capital opportunity with evidence capture, human review gates, and next-action recommendations. | F27: =HYPERLINK('Link Config'!$B$2&"plugins/vc/agents/vc-dealflow-concierge.md","Dealflow Concierge") | H27: =HYPERLINK('Link Config'!$B$2&"plugins/vc/alludium/documents/shared/template-use-guidance.md","Template Use Guidance (operating_guidance)") | I27: alludium-platform harmonic-mcp-oauth affinity-mcp-server exa-mcp-hosted brave-search-mcp serpapi-mcp firecrawl-mcp-hosted dealroom-mcp google_drive | J27: request-founder-materials | K27: general
A28: Alex | B28: Deal Pipeline | C28: General | D28: =HYPERLINK('Link Config'!$B$2&"plugins/vc/tasks/summarize-initial-call.md","Summarize Meeting Records") | E28: Summarize or ingest meeting records for one venture-capital opportunity with evidence capture, human review gates, and next-action recommendations. | F28: =HYPERLINK('Link Config'!$B$2&"plugins/vc/agents/vc-meeting-operator.md","Meeting Operator") | G28: =HYPERLINK('Link Config'!$B$2&"plugins/vc/skills/meeting-prep-and-summary/SKILL.md","Meeting Prep & Summary") | H28: =HYPERLINK('Link Config'!$B$2&"plugins/vc/alludium/documents/deal-room/customer-insights-summary-template.md","Customer Insights Summary Template (output_template, to customer_insights_artifact_id)") | I28: alludium-platform harmonic-mcp-oauth affinity-mcp-server exa-mcp-hosted brave-search-mcp serpapi-mcp firecrawl-mcp-hosted dealroom-mcp granola-mcp google_drive | J28: summarize-initial-call | K28: general
A29: Alex | B29: Deal Pipeline | C29: General | D29: =HYPERLINK('Link Config'!$B$2&"plugins/vc/tasks/summarize-initial-call.md","Summarize Meeting Records") | E29: Summarize or ingest meeting records for one venture-capital opportunity with evidence capture, human review gates, and next-action recommendations. | F29: =HYPERLINK('Link Config'!$B$2&"plugins/vc/agents/vc-meeting-operator.md","Meeting Operator") | G29: =HYPERLINK('Link Config'!$B$2&"plugins/vc/skills/citation-enforcement/SKILL.md","Citation Enforcement") | H29: =HYPERLINK('Link Config'!$B$2&"plugins/vc/alludium/documents/shared/evidence-citation-style-guide.md","Evidence And Citation Style Guide (style_guide)") | I29: alludium-platform harmonic-mcp-oauth affinity-mcp-server exa-mcp-hosted brave-search-mcp serpapi-mcp firecrawl-mcp-hosted dealroom-mcp granola-mcp google_drive | J29: summarize-initial-call | K29: general
A30: Alex | B30: Deal Pipeline | C30: General | D30: =HYPERLINK('Link Config'!$B$2&"plugins/vc/tasks/summarize-initial-call.md","Summarize Meeting Records") | E30: Summarize or ingest meeting records for one venture-capital opportunity with evidence capture, human review gates, and next-action recommendations. | F30: =HYPERLINK('Link Config'!$B$2&"plugins/vc/agents/vc-meeting-operator.md","Meeting Operator") | G30: =HYPERLINK('Link Config'!$B$2&"plugins/vc/skills/vc-task-and-next-step-generation/SKILL.md","VC Task & Next-Step Generation") | H30: =HYPERLINK('Link Config'!$B$2&"plugins/vc/alludium/documents/shared/template-use-guidance.md","Template Use Guidance (operating_guidance)") | I30: alludium-platform harmonic-mcp-oauth affinity-mcp-server exa-mcp-hosted brave-search-mcp serpapi-mcp firecrawl-mcp-hosted dealroom-mcp granola-mcp google_drive | J30: summarize-initial-call | K30: general
B31: Deal Pipeline | C31: General | D31: =HYPERLINK('Link Config'!$B$2&"plugins/vc/tasks/review-opportunity-status.md","Review Opportunity Status") | E31: Review the current status of one venture-capital opportunity and suggest missing inputs, stage movement, and next tasks without producing a formal investment evaluation document. | F31: =HYPERLINK('Link Config'!$B$2&"plugins/vc/agents/vc-pipeline-autopilot.md","Pipeline Autopilot") | G31: =HYPERLINK('Link Config'!$B$2&"plugins/vc/skills/citation-enforcement/SKILL.md","Citation Enforcement") | H31: =HYPERLINK('Link Config'!$B$2&"plugins/vc/alludium/documents/deal-room/deal-room-sop.md","Deal Pipeline Operating SOP (operating_guidance)") | I31: alludium-platform affinity-mcp-server exa-mcp-hosted brave-search-mcp serpapi-mcp dealroom-mcp | J31: review-opportunity-status | K31: general
B32: Deal Pipeline | C32: General | D32: =HYPERLINK('Link Config'!$B$2&"plugins/vc/tasks/review-opportunity-status.md","Review Opportunity Status") | E32: Review the current status of one venture-capital opportunity and suggest missing inputs, stage movement, and next tasks without producing a formal investment evaluation document. | F32: =HYPERLINK('Link Config'!$B$2&"plugins/vc/agents/vc-pipeline-autopilot.md","Pipeline Autopilot") | G32: =HYPERLINK('Link Config'!$B$2&"plugins/vc/skills/vc-task-and-next-step-generation/SKILL.md","VC Task & Next-Step Generation") | H32: =HYPERLINK('Link Config'!$B$2&"plugins/vc/alludium/documents/shared/opportunity-evaluation-framework.md","Opportunity Evaluation Framework (methodology)") | I32: alludium-platform affinity-mcp-server exa-mcp-hosted brave-search-mcp serpapi-mcp dealroom-mcp | J32: review-opportunity-status | K32: general
B33: Deal Pipeline | C33: General | D33: =HYPERLINK('Link Config'!$B$2&"plugins/vc/tasks/review-opportunity-status.md","Review Opportunity Status") | E33: Review the current status of one venture-capital opportunity and suggest missing inputs, stage movement, and next tasks without producing a formal investment evaluation document. | F33: =HYPERLINK('Link Config'!$B$2&"plugins/vc/agents/vc-pipeline-autopilot.md","Pipeline Autopilot") | H33: =HYPERLINK('Link Config'!$B$2&"plugins/vc/alludium/documents/shared/evaluation-workstream-guide.md","Evaluation Workstream Guide (methodology)") | I33: alludium-platform affinity-mcp-server exa-mcp-hosted brave-search-mcp serpapi-mcp dealroom-mcp | J33: review-opportunity-status | K33: general
B34: Deal Pipeline | C34: General | D34: =HYPERLINK('Link Config'!$B$2&"plugins/vc/tasks/review-opportunity-status.md","Review Opportunity Status") | E34: Review the current status of one venture-capital opportunity and suggest missing inputs, stage movement, and next tasks without producing a formal investment evaluation document. | F34: =HYPERLINK('Link Config'!$B$2&"plugins/vc/agents/vc-pipeline-autopilot.md","Pipeline Autopilot") | H34: =HYPERLINK('Link Config'!$B$2&"plugins/vc/alludium/documents/shared/evidence-citation-style-guide.md","Evidence And Citation Style Guide (style_guide)") | I34: alludium-platform affinity-mcp-server exa-mcp-hosted brave-search-mcp serpapi-mcp dealroom-mcp | J34: review-opportunity-status | K34: general
B35: Deal Pipeline | C35: General | D35: =HYPERLINK('Link Config'!$B$2&"plugins/vc/tasks/review-opportunity-status.md","Review Opportunity Status") | E35: Review the current status of one venture-capital opportunity and suggest missing inputs, stage movement, and next tasks without producing a formal investment evaluation document. | F35: =HYPERLINK('Link Config'!$B$2&"plugins/vc/agents/vc-pipeline-autopilot.md","Pipeline Autopilot") | H35: =HYPERLINK('Link Config'!$B$2&"plugins/vc/alludium/documents/shared/template-use-guidance.md","Template Use Guidance (operating_guidance)") | I35: alludium-platform affinity-mcp-server exa-mcp-hosted brave-search-mcp serpapi-mcp dealroom-mcp | J35: review-opportunity-status | K35: general
B36: Deal Pipeline | C36: Integration Support | D36: =HYPERLINK('Link Config'!$B$2&"plugins/vc/tasks/affinity-sync-read.md","Preview Affinity Pipeline Import") | E36: Preview selected Affinity opportunity, company, person, note, and list-entry data before importing it into Deal Pipeline context. | F36: =HYPERLINK('Link Config'!$B$2&"plugins/vc/agents/vc-integration-operator.md","Integration Operator") | G36: =HYPERLINK('Link Config'!$B$2&"plugins/vc/skills/vc-affinity-sync-read/SKILL.md","VC Affinity Sync Read") | H36: None declared | I36: None declared | J36: affinity-sync-read | K36: project_management
B37: Deal Pipeline | C37: Integration Support | D37: =HYPERLINK('Link Config'!$B$2&"plugins/vc/tasks/affinity-sync-read.md","Preview Affinity Pipeline Import") | E37: Preview selected Affinity opportunity, company, person, note, and list-entry data before importing it into Deal Pipeline context. | F37: =HYPERLINK('Link Config'!$B$2&"plugins/vc/agents/vc-integration-operator.md","Integration Operator") | G37: =HYPERLINK('Link Config'!$B$2&"plugins/vc/skills/citation-enforcement/SKILL.md","Citation Enforcement") | I37: None declared | J37: affinity-sync-read | K37: project_management
B38: Deal Pipeline | C38: Integration Support | D38: =HYPERLINK('Link Config'!$B$2&"plugins/vc/tasks/affinity-sync-write.md","Draft Affinity Write-Back Proposals") | E38: Draft reviewable Affinity note, field, and stage update proposals from VC task outputs. | F38: =HYPERLINK('Link Config'!$B$2&"plugins/vc/agents/vc-integration-operator.md","Integration Operator") | G38: =HYPERLINK('Link Config'!$B$2&"plugins/vc/skills/vc-affinity-sync-write/SKILL.md","VC Affinity Sync Write") | H38: None declared | I38: None declared | J38: affinity-sync-write | K38: project_management
B39: Deal Pipeline | C39: Integration Support | D39: =HYPERLINK('Link Config'!$B$2&"plugins/vc/tasks/affinity-sync-write.md","Draft Affinity Write-Back Proposals") | E39: Draft reviewable Affinity note, field, and stage update proposals from VC task outputs. | F39: =HYPERLINK('Link Config'!$B$2&"plugins/vc/agents/vc-integration-operator.md","Integration Operator") | G39: =HYPERLINK('Link Config'!$B$2&"plugins/vc/skills/citation-enforcement/SKILL.md","Citation Enforcement") | I39: None declared | J39: affinity-sync-write | K39: project_management
B40: Deal Pipeline | C40: Integration Support | D40: =HYPERLINK('Link Config'!$B$2&"plugins/vc/tasks/google-drive-sync-write.md","Draft Google Drive File Proposals") | E40: Draft reviewable Google Drive file or comment proposals from VC task outputs without performing broad Drive mutations. | F40: =HYPERLINK('Link Config'!$B$2&"plugins/vc/agents/vc-integration-operator.md","Integration Operator") | G40: =HYPERLINK('Link Config'!$B$2&"plugins/vc/skills/vc-google-drive-sync-write/SKILL.md","VC Google Drive Sync Write") | H40: None declared | I40: None declared | J40: google-drive-sync-write | K40: project_management
B41: Deal Pipeline | C41: Integration Support | D41: =HYPERLINK('Link Config'!$B$2&"plugins/vc/tasks/google-drive-sync-write.md","Draft Google Drive File Proposals") | E41: Draft reviewable Google Drive file or comment proposals from VC task outputs without performing broad Drive mutations. | F41: =HYPERLINK('Link Config'!$B$2&"plugins/vc/agents/vc-integration-operator.md","Integration Operator") | G41: =HYPERLINK('Link Config'!$B$2&"plugins/vc/skills/citation-enforcement/SKILL.md","Citation Enforcement") | I41: None declared | J41: google-drive-sync-write | K41: project_management
B42: Deal Pipeline | C42: Integration Support | D42: =HYPERLINK('Link Config'!$B$2&"plugins/vc/tasks/notion-sync-write.md","Draft Notion Update Proposals") | E42: Draft reviewable Notion page, database, or comment proposals from VC task outputs without performing broad workspace mutation. | F42: =HYPERLINK('Link Config'!$B$2&"plugins/vc/agents/vc-integration-operator.md","Integration Operator") | G42: =HYPERLINK('Link Config'!$B$2&"plugins/vc/skills/vc-notion-sync-write/SKILL.md","VC Notion Sync Write") | H42: None declared | I42: None declared | J42: notion-sync-write | K42: project_management
B43: Deal Pipeline | C43: Integration Support | D43: =HYPERLINK('Link Config'!$B$2&"plugins/vc/tasks/notion-sync-write.md","Draft Notion Update Proposals") | E43: Draft reviewable Notion page, database, or comment proposals from VC task outputs without performing broad workspace mutation. | F43: =HYPERLINK('Link Config'!$B$2&"plugins/vc/agents/vc-integration-operator.md","Integration Operator") | G43: =HYPERLINK('Link Config'!$B$2&"plugins/vc/skills/citation-enforcement/SKILL.md","Citation Enforcement") | I43: None declared | J43: notion-sync-write | K43: project_management
B44: Deal Pipeline | C44: Integration Support | D44: =HYPERLINK('Link Config'!$B$2&"plugins/vc/tasks/slack-sync-write.md","Draft Slack Handoff Notifications") | E44: Draft approved Slack handoff notifications for VC workflows without broad posting. | F44: =HYPERLINK('Link Config'!$B$2&"plugins/vc/agents/vc-integration-operator.md","Integration Operator") | G44: =HYPERLINK('Link Config'!$B$2&"plugins/vc/skills/vc-slack-sync-write/SKILL.md","VC Slack Sync Write") | H44: None declared | I44: None declared | J44: slack-sync-write | K44: project_management
B45: Deal Pipeline | C45: Integration Support | D45: =HYPERLINK('Link Config'!$B$2&"plugins/vc/tasks/slack-sync-write.md","Draft Slack Handoff Notifications") | E45: Draft approved Slack handoff notifications for VC workflows without broad posting. | F45: =HYPERLINK('Link Config'!$B$2&"plugins/vc/agents/vc-integration-operator.md","Integration Operator") | G45: =HYPERLINK('Link Config'!$B$2&"plugins/vc/skills/citation-enforcement/SKILL.md","Citation Enforcement") | I45: None declared | J45: slack-sync-write | K45: project_management
B46: Deal Pipeline | C46: Integration Support | D46: =HYPERLINK('Link Config'!$B$2&"plugins/vc/tasks/affinity-discovery.md","Explore Affinity Lists and Stages") | E46: Discover Affinity list, stage, field, and object-count scope before Deal Pipeline import or sync. | F46: =HYPERLINK('Link Config'!$B$2&"plugins/vc/agents/vc-integration-operator.md","Integration Operator") | G46: =HYPERLINK('Link Config'!$B$2&"plugins/vc/skills/vc-affinity-discovery/SKILL.md","VC Affinity Discovery") | H46: None declared | I46: None declared | J46: affinity-discovery | K46: project_management
B47: Deal Pipeline | C47: Integration Support | D47: =HYPERLINK('Link Config'!$B$2&"plugins/vc/tasks/affinity-discovery.md","Explore Affinity Lists and Stages") | E47: Discover Affinity list, stage, field, and object-count scope before Deal Pipeline import or sync. | F47: =HYPERLINK('Link Config'!$B$2&"plugins/vc/agents/vc-integration-operator.md","Integration Operator") | G47: =HYPERLINK('Link Config'!$B$2&"plugins/vc/skills/citation-enforcement/SKILL.md","Citation Enforcement") | I47: None declared | J47: affinity-discovery | K47: project_management
B48: Deal Pipeline | C48: Integration Support | D48: =HYPERLINK('Link Config'!$B$2&"plugins/vc/tasks/google-drive-discovery.md","Explore Google Drive Sources") | E48: Discover Google Drive shared drive, folder, and file scope before selected Deal Pipeline context reads. | F48: =HYPERLINK('Link Config'!$B$2&"plugins/vc/agents/vc-integration-operator.md","Integration Operator") | G48: =HYPERLINK('Link Config'!$B$2&"plugins/vc/skills/vc-google-drive-discovery/SKILL.md","VC Google Drive Discovery") | H48: None declared | I48: None declared | J48: google-drive-discovery | K48: project_management
B49: Deal Pipeline | C49: Integration Support | D49: =HYPERLINK('Link Config'!$B$2&"plugins/vc/tasks/google-drive-discovery.md","Explore Google Drive Sources") | E49: Discover Google Drive shared drive, folder, and file scope before selected Deal Pipeline context reads. | F49: =HYPERLINK('Link Config'!$B$2&"plugins/vc/agents/vc-integration-operator.md","Integration Operator") | G49: =HYPERLINK('Link Config'!$B$2&"plugins/vc/skills/citation-enforcement/SKILL.md","Citation Enforcement") | I49: None declared | J49: google-drive-discovery | K49: project_management
B50: Deal Pipeline | C50: Integration Support | D50: =HYPERLINK('Link Config'!$B$2&"plugins/vc/tasks/harmonic-discovery.md","Explore Harmonic Source Scopes") | E50: Discover Harmonic saved searches, daily searches, and source scope before selected VC sourcing context reads. | F50: =HYPERLINK('Link Config'!$B$2&"plugins/vc/agents/vc-integration-operator.md","Integration Operator") | G50: =HYPERLINK('Link Config'!$B$2&"plugins/vc/skills/vc-harmonic-discovery/SKILL.md","VC Harmonic Discovery") | H50: None declared | I50: None declared | J50: harmonic-discovery | K50: project_management
B51: Deal Pipeline | C51: Integration Support | D51: =HYPERLINK('Link Config'!$B$2&"plugins/vc/tasks/harmonic-discovery.md","Explore Harmonic Source Scopes") | E51: Discover Harmonic saved searches, daily searches, and source scope before selected VC sourcing context reads. | F51: =HYPERLINK('Link Config'!$B$2&"plugins/vc/agents/vc-integration-operator.md","Integration Operator") | G51: =HYPERLINK('Link Config'!$B$2&"plugins/vc/skills/citation-enforcement/SKILL.md","Citation Enforcement") | I51: None declared | J51: harmonic-discovery | K51: project_management
B52: Deal Pipeline | C52: Integration Support | D52: =HYPERLINK('Link Config'!$B$2&"plugins/vc/tasks/notion-discovery.md","Explore Notion Pages and Databases") | E52: Discover Notion page, database, and workspace scope before selected Deal Pipeline context reads. | F52: =HYPERLINK('Link Config'!$B$2&"plugins/vc/agents/vc-integration-operator.md","Integration Operator") | G52: =HYPERLINK('Link Config'!$B$2&"plugins/vc/skills/vc-notion-discovery/SKILL.md","VC Notion Discovery") | H52: None declared | I52: None declared | J52: notion-discovery | K52: project_management
B53: Deal Pipeline | C53: Integration Support | D53: =HYPERLINK('Link Config'!$B$2&"plugins/vc/tasks/notion-discovery.md","Explore Notion Pages and Databases") | E53: Discover Notion page, database, and workspace scope before selected Deal Pipeline context reads. | F53: =HYPERLINK('Link Config'!$B$2&"plugins/vc/agents/vc-integration-operator.md","Integration Operator") | G53: =HYPERLINK('Link Config'!$B$2&"plugins/vc/skills/citation-enforcement/SKILL.md","Citation Enforcement") | I53: None declared | J53: notion-discovery | K53: project_management
B54: Deal Pipeline | C54: Integration Support | D54: =HYPERLINK('Link Config'!$B$2&"plugins/vc/tasks/slack-discovery.md","Explore Slack Channels for VC Context") | E54: Discover Slack workspace and channel scope before selected VC context reads or handoff notifications. | F54: =HYPERLINK('Link Config'!$B$2&"plugins/vc/agents/vc-integration-operator.md","Integration Operator") | G54: =HYPERLINK('Link Config'!$B$2&"plugins/vc/skills/vc-slack-discovery/SKILL.md","VC Slack Discovery") | H54: None declared | I54: None declared | J54: slack-discovery | K54: project_management
B55: Deal Pipeline | C55: Integration Support | D55: =HYPERLINK('Link Config'!$B$2&"plugins/vc/tasks/slack-discovery.md","Explore Slack Channels for VC Context") | E55: Discover Slack workspace and channel scope before selected VC context reads or handoff notifications. | F55: =HYPERLINK('Link Config'!$B$2&"plugins/vc/agents/vc-integration-operator.md","Integration Operator") | G55: =HYPERLINK('Link Config'!$B$2&"plugins/vc/skills/citation-enforcement/SKILL.md","Citation Enforcement") | I55: None declared | J55: slack-discovery | K55: project_management
B56: Deal Pipeline | C56: Pipeline Management | D56: =HYPERLINK('Link Config'!$B$2&"plugins/vc/tasks/prepare-deal-flow-agenda.md","Prepare Deal Flow Agenda") | E56: Prepare Deal Flow Agenda for one venture-capital opportunity with evidence capture, human review gates, and next-action recommendations. | F56: =HYPERLINK('Link Config'!$B$2&"plugins/vc/agents/vc-pipeline-autopilot.md","Pipeline Autopilot") | G56: =HYPERLINK('Link Config'!$B$2&"plugins/vc/skills/citation-enforcement/SKILL.md","Citation Enforcement") | H56: None declared | I56: alludium-platform affinity-mcp-server exa-mcp-hosted brave-search-mcp serpapi-mcp dealroom-mcp | J56: prepare-deal-flow-agenda | K56: project_management
B57: Deal Pipeline | C57: Pipeline Management | D57: =HYPERLINK('Link Config'!$B$2&"plugins/vc/tasks/prepare-deal-flow-agenda.md","Prepare Deal Flow Agenda") | E57: Prepare Deal Flow Agenda for one venture-capital opportunity with evidence capture, human review gates, and next-action recommendations. | F57: =HYPERLINK('Link Config'!$B$2&"plugins/vc/agents/vc-pipeline-autopilot.md","Pipeline Autopilot") | G57: =HYPERLINK('Link Config'!$B$2&"plugins/vc/skills/vc-task-and-next-step-generation/SKILL.md","VC Task & Next-Step Generation") | I57: alludium-platform affinity-mcp-server exa-mcp-hosted brave-search-mcp serpapi-mcp dealroom-mcp | J57: prepare-deal-flow-agenda | K57: project_management
B58: Deal Pipeline | C58: Integration Support | D58: =HYPERLINK('Link Config'!$B$2&"plugins/vc/tasks/google-drive-sync-read.md","Preview Google Drive Context") | E58: Preview selected Google Drive file, folder, and document context before attaching or importing it into Deal Pipeline tasks. | F58: =HYPERLINK('Link Config'!$B$2&"plugins/vc/agents/vc-integration-operator.md","Integration Operator") | G58: =HYPERLINK('Link Config'!$B$2&"plugins/vc/skills/vc-google-drive-sync-read/SKILL.md","VC Google Drive Sync Read") | H58: None declared | I58: None declared | J58: google-drive-sync-read | K58: project_management
B59: Deal Pipeline | C59: Integration Support | D59: =HYPERLINK('Link Config'!$B$2&"plugins/vc/tasks/google-drive-sync-read.md","Preview Google Drive Context") | E59: Preview selected Google Drive file, folder, and document context before attaching or importing it into Deal Pipeline tasks. | F59: =HYPERLINK('Link Config'!$B$2&"plugins/vc/agents/vc-integration-operator.md","Integration Operator") | G59: =HYPERLINK('Link Config'!$B$2&"plugins/vc/skills/citation-enforcement/SKILL.md","Citation Enforcement") | I59: None declared | J59: google-drive-sync-read | K59: project_management
B60: Deal Pipeline | C60: Integration Support | D60: =HYPERLINK('Link Config'!$B$2&"plugins/vc/tasks/harmonic-sync-read.md","Preview Harmonic Search Results") | E60: Preview selected Harmonic company or saved-search results before using them as VC sourcing or screening context. | F60: =HYPERLINK('Link Config'!$B$2&"plugins/vc/agents/vc-integration-operator.md","Integration Operator") | G60: =HYPERLINK('Link Config'!$B$2&"plugins/vc/skills/vc-harmonic-sync-read/SKILL.md","VC Harmonic Sync Read") | H60: None declared | I60: None declared | J60: harmonic-sync-read | K60: project_management
B61: Deal Pipeline | C61: Integration Support | D61: =HYPERLINK('Link Config'!$B$2&"plugins/vc/tasks/harmonic-sync-read.md","Preview Harmonic Search Results") | E61: Preview selected Harmonic company or saved-search results before using them as VC sourcing or screening context. | F61: =HYPERLINK('Link Config'!$B$2&"plugins/vc/agents/vc-integration-operator.md","Integration Operator") | G61: =HYPERLINK('Link Config'!$B$2&"plugins/vc/skills/citation-enforcement/SKILL.md","Citation Enforcement") | I61: None declared | J61: harmonic-sync-read | K61: project_management
B62: Deal Pipeline | C62: Integration Support | D62: =HYPERLINK('Link Config'!$B$2&"plugins/vc/tasks/notion-sync-read.md","Preview Notion Context") | E62: Preview selected Notion page, block, property, and database content before attaching it to Deal Pipeline tasks. | F62: =HYPERLINK('Link Config'!$B$2&"plugins/vc/agents/vc-integration-operator.md","Integration Operator") | G62: =HYPERLINK('Link Config'!$B$2&"plugins/vc/skills/vc-notion-sync-read/SKILL.md","VC Notion Sync Read") | H62: None declared | I62: None declared | J62: notion-sync-read | K62: project_management
B63: Deal Pipeline | C63: Integration Support | D63: =HYPERLINK('Link Config'!$B$2&"plugins/vc/tasks/notion-sync-read.md","Preview Notion Context") | E63: Preview selected Notion page, block, property, and database content before attaching it to Deal Pipeline tasks. | F63: =HYPERLINK('Link Config'!$B$2&"plugins/vc/agents/vc-integration-operator.md","Integration Operator") | G63: =HYPERLINK('Link Config'!$B$2&"plugins/vc/skills/citation-enforcement/SKILL.md","Citation Enforcement") | I63: None declared | J63: notion-sync-read | K63: project_management
B64: Deal Pipeline | C64: Integration Support | D64: =HYPERLINK('Link Config'!$B$2&"plugins/vc/tasks/slack-sync-read.md","Preview Slack Deal Context") | E64: Preview selected Slack channel, thread, message, and file context for Deal Pipeline tasks. | F64: =HYPERLINK('Link Config'!$B$2&"plugins/vc/agents/vc-integration-operator.md","Integration Operator") | G64: =HYPERLINK('Link Config'!$B$2&"plugins/vc/skills/vc-slack-sync-read/SKILL.md","VC Slack Sync Read") | H64: None declared | I64: None declared | J64: slack-sync-read | K64: project_management
B65: Deal Pipeline | C65: Integration Support | D65: =HYPERLINK('Link Config'!$B$2&"plugins/vc/tasks/slack-sync-read.md","Preview Slack Deal Context") | E65: Preview selected Slack channel, thread, message, and file context for Deal Pipeline tasks. | F65: =HYPERLINK('Link Config'!$B$2&"plugins/vc/agents/vc-integration-operator.md","Integration Operator") | G65: =HYPERLINK('Link Config'!$B$2&"plugins/vc/skills/citation-enforcement/SKILL.md","Citation Enforcement") | I65: None declared | J65: slack-sync-read | K65: project_management
B66: Deal Pipeline | C66: Integration Support | D66: =HYPERLINK('Link Config'!$B$2&"plugins/vc/tasks/google-drive-setup.md","Set Up Google Drive for Deal Pipelines") | E66: Coordinate Google Drive connection readiness, folder discovery, read-preview policy, and optional file proposal scope for Deal Pipeline setup. | F66: =HYPERLINK('Link Config'!$B$2&"plugins/vc/agents/vc-integration-operator.md","Integration Operator") | G66: =HYPERLINK('Link Config'!$B$2&"plugins/vc/skills/vc-google-drive-discovery/SKILL.md","VC Google Drive Discovery") | H66: None declared | I66: google_drive | J66: google-drive-setup | K66: project_management
B67: Deal Pipeline | C67: Integration Support | D67: =HYPERLINK('Link Config'!$B$2&"plugins/vc/tasks/google-drive-setup.md","Set Up Google Drive for Deal Pipelines") | E67: Coordinate Google Drive connection readiness, folder discovery, read-preview policy, and optional file proposal scope for Deal Pipeline setup. | F67: =HYPERLINK('Link Config'!$B$2&"plugins/vc/agents/vc-integration-operator.md","Integration Operator") | G67: =HYPERLINK('Link Config'!$B$2&"plugins/vc/skills/vc-google-drive-sync-read/SKILL.md","VC Google Drive Sync Read") | I67: google_drive | J67: google-drive-setup | K67: project_management
B68: Deal Pipeline | C68: Integration Support | D68: =HYPERLINK('Link Config'!$B$2&"plugins/vc/tasks/google-drive-setup.md","Set Up Google Drive for Deal Pipelines") | E68: Coordinate Google Drive connection readiness, folder discovery, read-preview policy, and optional file proposal scope for Deal Pipeline setup. | F68: =HYPERLINK('Link Config'!$B$2&"plugins/vc/agents/vc-integration-operator.md","Integration Operator") | G68: =HYPERLINK('Link Config'!$B$2&"plugins/vc/skills/vc-google-drive-sync-write/SKILL.md","VC Google Drive Sync Write") | I68: google_drive | J68: google-drive-setup | K68: project_management
B69: Deal Pipeline | C69: Integration Support | D69: =HYPERLINK('Link Config'!$B$2&"plugins/vc/tasks/google-drive-setup.md","Set Up Google Drive for Deal Pipelines") | E69: Coordinate Google Drive connection readiness, folder discovery, read-preview policy, and optional file proposal scope for Deal Pipeline setup. | F69: =HYPERLINK('Link Config'!$B$2&"plugins/vc/agents/vc-integration-operator.md","Integration Operator") | G69: =HYPERLINK('Link Config'!$B$2&"plugins/vc/skills/citation-enforcement/SKILL.md","Citation Enforcement") | I69: google_drive | J69: google-drive-setup | K69: project_management
B70: Deal Pipeline | C70: Integration Support | D70: =HYPERLINK('Link Config'!$B$2&"plugins/vc/tasks/harmonic-setup.md","Set Up Harmonic for Deal Pipelines") | E70: Coordinate Harmonic connection readiness, saved-search discovery, and read-preview policy for Deal Pipeline setup. | F70: =HYPERLINK('Link Config'!$B$2&"plugins/vc/agents/vc-integration-operator.md","Integration Operator") | G70: =HYPERLINK('Link Config'!$B$2&"plugins/vc/skills/vc-harmonic-discovery/SKILL.md","VC Harmonic Discovery") | H70: None declared | I70: harmonic-mcp-oauth | J70: harmonic-setup | K70: project_management
B71: Deal Pipeline | C71: Integration Support | D71: =HYPERLINK('Link Config'!$B$2&"plugins/vc/tasks/harmonic-setup.md","Set Up Harmonic for Deal Pipelines") | E71: Coordinate Harmonic connection readiness, saved-search discovery, and read-preview policy for Deal Pipeline setup. | F71: =HYPERLINK('Link Config'!$B$2&"plugins/vc/agents/vc-integration-operator.md","Integration Operator") | G71: =HYPERLINK('Link Config'!$B$2&"plugins/vc/skills/vc-harmonic-sync-read/SKILL.md","VC Harmonic Sync Read") | I71: harmonic-mcp-oauth | J71: harmonic-setup | K71: project_management
B72: Deal Pipeline | C72: Integration Support | D72: =HYPERLINK('Link Config'!$B$2&"plugins/vc/tasks/harmonic-setup.md","Set Up Harmonic for Deal Pipelines") | E72: Coordinate Harmonic connection readiness, saved-search discovery, and read-preview policy for Deal Pipeline setup. | F72: =HYPERLINK('Link Config'!$B$2&"plugins/vc/agents/vc-integration-operator.md","Integration Operator") | G72: =HYPERLINK('Link Config'!$B$2&"plugins/vc/skills/citation-enforcement/SKILL.md","Citation Enforcement") | I72: harmonic-mcp-oauth | J72: harmonic-setup | K72: project_management
B73: Deal Pipeline | C73: Integration Support | D73: =HYPERLINK('Link Config'!$B$2&"plugins/vc/tasks/notion-setup.md","Set Up Notion for Deal Pipelines") | E73: Coordinate Notion connection readiness, page/database discovery, read-preview policy, and optional update-proposal scope for Deal Pipeline setup. | F73: =HYPERLINK('Link Config'!$B$2&"plugins/vc/agents/vc-integration-operator.md","Integration Operator") | G73: =HYPERLINK('Link Config'!$B$2&"plugins/vc/skills/vc-notion-discovery/SKILL.md","VC Notion Discovery") | H73: None declared | I73: notion | J73: notion-setup | K73: project_management
B74: Deal Pipeline | C74: Integration Support | D74: =HYPERLINK('Link Config'!$B$2&"plugins/vc/tasks/notion-setup.md","Set Up Notion for Deal Pipelines") | E74: Coordinate Notion connection readiness, page/database discovery, read-preview policy, and optional update-proposal scope for Deal Pipeline setup. | F74: =HYPERLINK('Link Config'!$B$2&"plugins/vc/agents/vc-integration-operator.md","Integration Operator") | G74: =HYPERLINK('Link Config'!$B$2&"plugins/vc/skills/vc-notion-sync-read/SKILL.md","VC Notion Sync Read") | I74: notion | J74: notion-setup | K74: project_management
B75: Deal Pipeline | C75: Integration Support | D75: =HYPERLINK('Link Config'!$B$2&"plugins/vc/tasks/notion-setup.md","Set Up Notion for Deal Pipelines") | E75: Coordinate Notion connection readiness, page/database discovery, read-preview policy, and optional update-proposal scope for Deal Pipeline setup. | F75: =HYPERLINK('Link Config'!$B$2&"plugins/vc/agents/vc-integration-operator.md","Integration Operator") | G75: =HYPERLINK('Link Config'!$B$2&"plugins/vc/skills/vc-notion-sync-write/SKILL.md","VC Notion Sync Write") | I75: notion | J75: notion-setup | K75: project_management
B76: Deal Pipeline | C76: Integration Support | D76: =HYPERLINK('Link Config'!$B$2&"plugins/vc/tasks/notion-setup.md","Set Up Notion for Deal Pipelines") | E76: Coordinate Notion connection readiness, page/database discovery, read-preview policy, and optional update-proposal scope for Deal Pipeline setup. | F76: =HYPERLINK('Link Config'!$B$2&"plugins/vc/agents/vc-integration-operator.md","Integration Operator") | G76: =HYPERLINK('Link Config'!$B$2&"plugins/vc/skills/citation-enforcement/SKILL.md","Citation Enforcement") | I76: notion | J76: notion-setup | K76: project_management
B77: Deal Pipeline | C77: Integration Support | D77: =HYPERLINK('Link Config'!$B$2&"plugins/vc/tasks/slack-setup.md","Set Up Slack for Deal Pipelines") | E77: Coordinate Slack connection readiness, channel discovery, read-preview policy, and optional notification proposal scope for Deal Pipeline setup. | F77: =HYPERLINK('Link Config'!$B$2&"plugins/vc/agents/vc-integration-operator.md","Integration Operator") | G77: =HYPERLINK('Link Config'!$B$2&"plugins/vc/skills/vc-slack-discovery/SKILL.md","VC Slack Discovery") | H77: None declared | I77: slack_v2 | J77: slack-setup | K77: project_management
B78: Deal Pipeline | C78: Integration Support | D78: =HYPERLINK('Link Config'!$B$2&"plugins/vc/tasks/slack-setup.md","Set Up Slack for Deal Pipelines") | E78: Coordinate Slack connection readiness, channel discovery, read-preview policy, and optional notification proposal scope for Deal Pipeline setup. | F78: =HYPERLINK('Link Config'!$B$2&"plugins/vc/agents/vc-integration-operator.md","Integration Operator") | G78: =HYPERLINK('Link Config'!$B$2&"plugins/vc/skills/vc-slack-sync-read/SKILL.md","VC Slack Sync Read") | I78: slack_v2 | J78: slack-setup | K78: project_management
B79: Deal Pipeline | C79: Integration Support | D79: =HYPERLINK('Link Config'!$B$2&"plugins/vc/tasks/slack-setup.md","Set Up Slack for Deal Pipelines") | E79: Coordinate Slack connection readiness, channel discovery, read-preview policy, and optional notification proposal scope for Deal Pipeline setup. | F79: =HYPERLINK('Link Config'!$B$2&"plugins/vc/agents/vc-integration-operator.md","Integration Operator") | G79: =HYPERLINK('Link Config'!$B$2&"plugins/vc/skills/vc-slack-sync-write/SKILL.md","VC Slack Sync Write") | I79: slack_v2 | J79: slack-setup | K79: project_management
B80: Deal Pipeline | C80: Integration Support | D80: =HYPERLINK('Link Config'!$B$2&"plugins/vc/tasks/slack-setup.md","Set Up Slack for Deal Pipelines") | E80: Coordinate Slack connection readiness, channel discovery, read-preview policy, and optional notification proposal scope for Deal Pipeline setup. | F80: =HYPERLINK('Link Config'!$B$2&"plugins/vc/agents/vc-integration-operator.md","Integration Operator") | G80: =HYPERLINK('Link Config'!$B$2&"plugins/vc/skills/citation-enforcement/SKILL.md","Citation Enforcement") | I80: slack_v2 | J80: slack-setup | K80: project_management
A81: Barry | B81: Deal Pipeline | C81: Screening | D81: =HYPERLINK('Link Config'!$B$2&"plugins/vc/tasks/run-investment-screen.md","Run Investment Fit Screen") | E81: Run a fast investment fit screen for one venture-capital opportunity using configured criteria, available evidence, human review gates, and next-action recommendations. | F81: =HYPERLINK('Link Config'!$B$2&"plugins/vc/agents/vc-first-look-analyst.md","First Look Analyst") | G81: =HYPERLINK('Link Config'!$B$2&"plugins/vc/skills/investment-screening-framework/SKILL.md","Investment Screening Framework") | H81: =HYPERLINK('Link Config'!$B$2&"plugins/vc/alludium/documents/shared/investment-screening-framework.md","Investment Screening Framework (methodology, to investment_screen_scorecard_artifact_id)") | I81: alludium-platform harmonic-mcp-oauth affinity-mcp-server exa-mcp-hosted brave-search-mcp serpapi-mcp firecrawl-mcp-hosted dealroom-mcp | J81: run-investment-screen | K81: project_instance
A82: Barry | B82: Deal Pipeline | C82: Screening | D82: =HYPERLINK('Link Config'!$B$2&"plugins/vc/tasks/run-investment-screen.md","Run Investment Fit Screen") | E82: Run a fast investment fit screen for one venture-capital opportunity using configured criteria, available evidence, human review gates, and next-action recommendations. | F82: =HYPERLINK('Link Config'!$B$2&"plugins/vc/agents/vc-first-look-analyst.md","First Look Analyst") | G82: =HYPERLINK('Link Config'!$B$2&"plugins/vc/skills/red-flags-scanner/SKILL.md","Red Flags Scanner") | H82: =HYPERLINK('Link Config'!$B$2&"plugins/vc/alludium/documents/shared/evidence-citation-style-guide.md","Evidence And Citation Style Guide (style_guide)") | I82: alludium-platform harmonic-mcp-oauth affinity-mcp-server exa-mcp-hosted brave-search-mcp serpapi-mcp firecrawl-mcp-hosted dealroom-mcp | J82: run-investment-screen | K82: project_instance
A83: Barry | B83: Deal Pipeline | C83: Screening | D83: =HYPERLINK('Link Config'!$B$2&"plugins/vc/tasks/run-investment-screen.md","Run Investment Fit Screen") | E83: Run a fast investment fit screen for one venture-capital opportunity using configured criteria, available evidence, human review gates, and next-action recommendations. | F83: =HYPERLINK('Link Config'!$B$2&"plugins/vc/agents/vc-first-look-analyst.md","First Look Analyst") | G83: =HYPERLINK('Link Config'!$B$2&"plugins/vc/skills/citation-enforcement/SKILL.md","Citation Enforcement") | H83: =HYPERLINK('Link Config'!$B$2&"plugins/vc/alludium/documents/shared/template-use-guidance.md","Template Use Guidance (operating_guidance)") | I83: alludium-platform harmonic-mcp-oauth affinity-mcp-server exa-mcp-hosted brave-search-mcp serpapi-mcp firecrawl-mcp-hosted dealroom-mcp | J83: run-investment-screen | K83: project_instance
B84: Deal Pipeline | C84: Evaluation | D84: =HYPERLINK('Link Config'!$B$2&"plugins/vc/tasks/run-follow-up-evaluation.md","Run Opportunity Evaluation") | E84: Run a deeper opportunity evaluation after screening for one venture-capital opportunity with evidence capture, human review gates, and next-action recommendations. | F84: =HYPERLINK('Link Config'!$B$2&"plugins/vc/agents/vc-evaluation-analyst.md","Evaluation Analyst") | G84: =HYPERLINK('Link Config'!$B$2&"plugins/vc/skills/investment-diligence-question-framework/SKILL.md","Investment Diligence Question Framework") | H84: =HYPERLINK('Link Config'!$B$2&"plugins/vc/alludium/documents/deal-room/follow-up-evaluation-template.md","Opportunity Evaluation Template (output_template, to follow_up_evaluation_artifact_id)") | I84: alludium-platform harmonic-mcp-oauth affinity-mcp-server exa-mcp-hosted brave-search-mcp serpapi-mcp firecrawl-mcp-hosted dealroom-mcp | J84: run-follow-up-evaluation | K84: project_instance
B85: Deal Pipeline | C85: Evaluation | D85: =HYPERLINK('Link Config'!$B$2&"plugins/vc/tasks/run-follow-up-evaluation.md","Run Opportunity Evaluation") | E85: Run a deeper opportunity evaluation after screening for one venture-capital opportunity with evidence capture, human review gates, and next-action recommendations. | F85: =HYPERLINK('Link Config'!$B$2&"plugins/vc/agents/vc-evaluation-analyst.md","Evaluation Analyst") | G85: =HYPERLINK('Link Config'!$B$2&"plugins/vc/skills/red-flags-scanner/SKILL.md","Red Flags Scanner") | H85: =HYPERLINK('Link Config'!$B$2&"plugins/vc/alludium/documents/shared/opportunity-evaluation-framework.md","Opportunity Evaluation Framework (methodology)") | I85: alludium-platform harmonic-mcp-oauth affinity-mcp-server exa-mcp-hosted brave-search-mcp serpapi-mcp firecrawl-mcp-hosted dealroom-mcp | J85: run-follow-up-evaluation | K85: project_instance
B86: Deal Pipeline | C86: Evaluation | D86: =HYPERLINK('Link Config'!$B$2&"plugins/vc/tasks/run-follow-up-evaluation.md","Run Opportunity Evaluation") | E86: Run a deeper opportunity evaluation after screening for one venture-capital opportunity with evidence capture, human review gates, and next-action recommendations. | F86: =HYPERLINK('Link Config'!$B$2&"plugins/vc/agents/vc-evaluation-analyst.md","Evaluation Analyst") | G86: =HYPERLINK('Link Config'!$B$2&"plugins/vc/skills/citation-enforcement/SKILL.md","Citation Enforcement") | H86: =HYPERLINK('Link Config'!$B$2&"plugins/vc/alludium/documents/shared/evaluation-workstream-guide.md","Evaluation Workstream Guide (methodology)") | I86: alludium-platform harmonic-mcp-oauth affinity-mcp-server exa-mcp-hosted brave-search-mcp serpapi-mcp firecrawl-mcp-hosted dealroom-mcp | J86: run-follow-up-evaluation | K86: project_instance
B87: Deal Pipeline | C87: Evaluation | D87: =HYPERLINK('Link Config'!$B$2&"plugins/vc/tasks/run-follow-up-evaluation.md","Run Opportunity Evaluation") | E87: Run a deeper opportunity evaluation after screening for one venture-capital opportunity with evidence capture, human review gates, and next-action recommendations. | F87: =HYPERLINK('Link Config'!$B$2&"plugins/vc/agents/vc-evaluation-analyst.md","Evaluation Analyst") | H87: =HYPERLINK('Link Config'!$B$2&"plugins/vc/alludium/documents/deal-room/commercial-evaluation-guide.md","Commercial Evaluation Guide (methodology)") | I87: alludium-platform harmonic-mcp-oauth affinity-mcp-server exa-mcp-hosted brave-search-mcp serpapi-mcp firecrawl-mcp-hosted dealroom-mcp | J87: run-follow-up-evaluation | K87: project_instance
B88: Deal Pipeline | C88: Evaluation | D88: =HYPERLINK('Link Config'!$B$2&"plugins/vc/tasks/run-follow-up-evaluation.md","Run Opportunity Evaluation") | E88: Run a deeper opportunity evaluation after screening for one venture-capital opportunity with evidence capture, human review gates, and next-action recommendations. | F88: =HYPERLINK('Link Config'!$B$2&"plugins/vc/agents/vc-evaluation-analyst.md","Evaluation Analyst") | H88: =HYPERLINK('Link Config'!$B$2&"plugins/vc/alludium/documents/deal-room/technical-evaluation-guide.md","Technical Evaluation Guide (methodology)") | I88: alludium-platform harmonic-mcp-oauth affinity-mcp-server exa-mcp-hosted brave-search-mcp serpapi-mcp firecrawl-mcp-hosted dealroom-mcp | J88: run-follow-up-evaluation | K88: project_instance
B89: Deal Pipeline | C89: Evaluation | D89: =HYPERLINK('Link Config'!$B$2&"plugins/vc/tasks/run-follow-up-evaluation.md","Run Opportunity Evaluation") | E89: Run a deeper opportunity evaluation after screening for one venture-capital opportunity with evidence capture, human review gates, and next-action recommendations. | F89: =HYPERLINK('Link Config'!$B$2&"plugins/vc/agents/vc-evaluation-analyst.md","Evaluation Analyst") | H89: =HYPERLINK('Link Config'!$B$2&"plugins/vc/alludium/documents/deal-room/financial-evaluation-guide.md","Financial Evaluation Guide (methodology)") | I89: alludium-platform harmonic-mcp-oauth affinity-mcp-server exa-mcp-hosted brave-search-mcp serpapi-mcp firecrawl-mcp-hosted dealroom-mcp | J89: run-follow-up-evaluation | K89: project_instance
B90: Deal Pipeline | C90: Evaluation | D90: =HYPERLINK('Link Config'!$B$2&"plugins/vc/tasks/run-follow-up-evaluation.md","Run Opportunity Evaluation") | E90: Run a deeper opportunity evaluation after screening for one venture-capital opportunity with evidence capture, human review gates, and next-action recommendations. | F90: =HYPERLINK('Link Config'!$B$2&"plugins/vc/agents/vc-evaluation-analyst.md","Evaluation Analyst") | H90: =HYPERLINK('Link Config'!$B$2&"plugins/vc/alludium/documents/shared/evidence-citation-style-guide.md","Evidence And Citation Style Guide (style_guide)") | I90: alludium-platform harmonic-mcp-oauth affinity-mcp-server exa-mcp-hosted brave-search-mcp serpapi-mcp firecrawl-mcp-hosted dealroom-mcp | J90: run-follow-up-evaluation | K90: project_instance
B91: Deal Pipeline | C91: Evaluation | D91: =HYPERLINK('Link Config'!$B$2&"plugins/vc/tasks/run-follow-up-evaluation.md","Run Opportunity Evaluation") | E91: Run a deeper opportunity evaluation after screening for one venture-capital opportunity with evidence capture, human review gates, and next-action recommendations. | F91: =HYPERLINK('Link Config'!$B$2&"plugins/vc/agents/vc-evaluation-analyst.md","Evaluation Analyst") | H91: =HYPERLINK('Link Config'!$B$2&"plugins/vc/alludium/documents/shared/template-use-guidance.md","Template Use Guidance (operating_guidance)") | I91: alludium-platform harmonic-mcp-oauth affinity-mcp-server exa-mcp-hosted brave-search-mcp serpapi-mcp firecrawl-mcp-hosted dealroom-mcp | J91: run-follow-up-evaluation | K91: project_instance
B92: Deal Pipeline | C92: Evaluation | D92: =HYPERLINK('Link Config'!$B$2&"plugins/vc/tasks/run-commercial-evaluation.md","Run Commercial Evaluation") | E92: Run an evaluation-stage commercial workstream for one venture-capital opportunity, identifying market/customer evidence, GTM risk, and next proof needed before formal diligence. | F92: =HYPERLINK('Link Config'!$B$2&"plugins/vc/agents/vc-evaluation-analyst.md","Evaluation Analyst") | G92: =HYPERLINK('Link Config'!$B$2&"plugins/vc/skills/commercial-evaluation-and-market-risk/SKILL.md","Commercial Evaluation & Market Risk") | H92: =HYPERLINK('Link Config'!$B$2&"plugins/vc/alludium/documents/deal-room/commercial-evaluation-template.md","Commercial Evaluation Template (output_template, to commercial_evaluation_artifact_id)") | I92: alludium-platform harmonic-mcp-oauth affinity-mcp-server exa-mcp-hosted brave-search-mcp serpapi-mcp firecrawl-mcp-hosted dealroom-mcp | J92: run-commercial-evaluation | K92: project_instance
B93: Deal Pipeline | C93: Evaluation | D93: =HYPERLINK('Link Config'!$B$2&"plugins/vc/tasks/run-commercial-evaluation.md","Run Commercial Evaluation") | E93: Run an evaluation-stage commercial workstream for one venture-capital opportunity, identifying market/customer evidence, GTM risk, and next proof needed before formal diligence. | F93: =HYPERLINK('Link Config'!$B$2&"plugins/vc/agents/vc-evaluation-analyst.md","Evaluation Analyst") | G93: =HYPERLINK('Link Config'!$B$2&"plugins/vc/skills/citation-enforcement/SKILL.md","Citation Enforcement") | H93: =HYPERLINK('Link Config'!$B$2&"plugins/vc/alludium/documents/shared/evaluation-workstream-guide.md","Evaluation Workstream Guide (methodology)") | I93: alludium-platform harmonic-mcp-oauth affinity-mcp-server exa-mcp-hosted brave-search-mcp serpapi-mcp firecrawl-mcp-hosted dealroom-mcp | J93: run-commercial-evaluation | K93: project_instance
B94: Deal Pipeline | C94: Evaluation | D94: =HYPERLINK('Link Config'!$B$2&"plugins/vc/tasks/run-commercial-evaluation.md","Run Commercial Evaluation") | E94: Run an evaluation-stage commercial workstream for one venture-capital opportunity, identifying market/customer evidence, GTM risk, and next proof needed before formal diligence. | F94: =HYPERLINK('Link Config'!$B$2&"plugins/vc/agents/vc-evaluation-analyst.md","Evaluation Analyst") | H94: =HYPERLINK('Link Config'!$B$2&"plugins/vc/alludium/documents/deal-room/commercial-evaluation-guide.md","Commercial Evaluation Guide (methodology)") | I94: alludium-platform harmonic-mcp-oauth affinity-mcp-server exa-mcp-hosted brave-search-mcp serpapi-mcp firecrawl-mcp-hosted dealroom-mcp | J94: run-commercial-evaluation | K94: project_instance
B95: Deal Pipeline | C95: Evaluation | D95: =HYPERLINK('Link Config'!$B$2&"plugins/vc/tasks/run-commercial-evaluation.md","Run Commercial Evaluation") | E95: Run an evaluation-stage commercial workstream for one venture-capital opportunity, identifying market/customer evidence, GTM risk, and next proof needed before formal diligence. | F95: =HYPERLINK('Link Config'!$B$2&"plugins/vc/agents/vc-evaluation-analyst.md","Evaluation Analyst") | H95: =HYPERLINK('Link Config'!$B$2&"plugins/vc/alludium/documents/shared/opportunity-evaluation-framework.md","Opportunity Evaluation Framework (methodology)") | I95: alludium-platform harmonic-mcp-oauth affinity-mcp-server exa-mcp-hosted brave-search-mcp serpapi-mcp firecrawl-mcp-hosted dealroom-mcp | J95: run-commercial-evaluation | K95: project_instance
B96: Deal Pipeline | C96: Evaluation | D96: =HYPERLINK('Link Config'!$B$2&"plugins/vc/tasks/run-commercial-evaluation.md","Run Commercial Evaluation") | E96: Run an evaluation-stage commercial workstream for one venture-capital opportunity, identifying market/customer evidence, GTM risk, and next proof needed before formal diligence. | F96: =HYPERLINK('Link Config'!$B$2&"plugins/vc/agents/vc-evaluation-analyst.md","Evaluation Analyst") | H96: =HYPERLINK('Link Config'!$B$2&"plugins/vc/alludium/documents/shared/evidence-citation-style-guide.md","Evidence And Citation Style Guide (style_guide)") | I96: alludium-platform harmonic-mcp-oauth affinity-mcp-server exa-mcp-hosted brave-search-mcp serpapi-mcp firecrawl-mcp-hosted dealroom-mcp | J96: run-commercial-evaluation | K96: project_instance
B97: Deal Pipeline | C97: Evaluation | D97: =HYPERLINK('Link Config'!$B$2&"plugins/vc/tasks/run-commercial-evaluation.md","Run Commercial Evaluation") | E97: Run an evaluation-stage commercial workstream for one venture-capital opportunity, identifying market/customer evidence, GTM risk, and next proof needed before formal diligence. | F97: =HYPERLINK('Link Config'!$B$2&"plugins/vc/agents/vc-evaluation-analyst.md","Evaluation Analyst") | H97: =HYPERLINK('Link Config'!$B$2&"plugins/vc/alludium/documents/shared/template-use-guidance.md","Template Use Guidance (operating_guidance)") | I97: alludium-platform harmonic-mcp-oauth affinity-mcp-server exa-mcp-hosted brave-search-mcp serpapi-mcp firecrawl-mcp-hosted dealroom-mcp | J97: run-commercial-evaluation | K97: project_instance
B98: Deal Pipeline | C98: Evaluation | D98: =HYPERLINK('Link Config'!$B$2&"plugins/vc/tasks/run-technical-evaluation.md","Run Technical Evaluation") | E98: Run an evaluation-stage technical and product workstream for one venture-capital opportunity, identifying product evidence, technical risk, and next proof needed before formal diligence. | F98: =HYPERLINK('Link Config'!$B$2&"plugins/vc/agents/vc-evaluation-analyst.md","Evaluation Analyst") | G98: =HYPERLINK('Link Config'!$B$2&"plugins/vc/skills/technical-evaluation-and-product-risk/SKILL.md","Technical Evaluation & Product Risk") | H98: =HYPERLINK('Link Config'!$B$2&"plugins/vc/alludium/documents/deal-room/technical-evaluation-template.md","Technical Evaluation Template (output_template, to technical_evaluation_artifact_id)") | I98: alludium-platform harmonic-mcp-oauth affinity-mcp-server exa-mcp-hosted brave-search-mcp serpapi-mcp firecrawl-mcp-hosted dealroom-mcp | J98: run-technical-evaluation | K98: project_instance
B99: Deal Pipeline | C99: Evaluation | D99: =HYPERLINK('Link Config'!$B$2&"plugins/vc/tasks/run-technical-evaluation.md","Run Technical Evaluation") | E99: Run an evaluation-stage technical and product workstream for one venture-capital opportunity, identifying product evidence, technical risk, and next proof needed before formal diligence. | F99: =HYPERLINK('Link Config'!$B$2&"plugins/vc/agents/vc-evaluation-analyst.md","Evaluation Analyst") | G99: =HYPERLINK('Link Config'!$B$2&"plugins/vc/skills/red-flags-scanner/SKILL.md","Red Flags Scanner") | H99: =HYPERLINK('Link Config'!$B$2&"plugins/vc/alludium/documents/shared/evaluation-workstream-guide.md","Evaluation Workstream Guide (methodology)") | I99: alludium-platform harmonic-mcp-oauth affinity-mcp-server exa-mcp-hosted brave-search-mcp serpapi-mcp firecrawl-mcp-hosted dealroom-mcp | J99: run-technical-evaluation | K99: project_instance
B100: Deal Pipeline | C100: Evaluation | D100: =HYPERLINK('Link Config'!$B$2&"plugins/vc/tasks/run-technical-evaluation.md","Run Technical Evaluation") | E100: Run an evaluation-stage technical and product workstream for one venture-capital opportunity, identifying product evidence, technical risk, and next proof needed before formal diligence. | F100: =HYPERLINK('Link Config'!$B$2&"plugins/vc/agents/vc-evaluation-analyst.md","Evaluation Analyst") | G100: =HYPERLINK('Link Config'!$B$2&"plugins/vc/skills/citation-enforcement/SKILL.md","Citation Enforcement") | H100: =HYPERLINK('Link Config'!$B$2&"plugins/vc/alludium/documents/deal-room/technical-evaluation-guide.md","Technical Evaluation Guide (methodology)") | I100: alludium-platform harmonic-mcp-oauth affinity-mcp-server exa-mcp-hosted brave-search-mcp serpapi-mcp firecrawl-mcp-hosted dealroom-mcp | J100: run-technical-evaluation | K100: project_instance
...

Sheet Skill Map
A1: Assigned | B1: Skill | C1: Agent Usage Count | D1: All Task Usage Count | E1: Project Task Usage Count | F1: Setup / Management Task Usage Count | G1: Agents | H1: Project Tasks
A2: Owner | B2: Linked skill | C2: Agents using skill | D2: All task rows | E2: Project-instance task rows | F2: Setup/general/management task rows | G2: Agents | H2: Tasks
B3: =HYPERLINK('Link Config'!$B$2&"plugins/vc/skills/citation-enforcement/SKILL.md","Citation Enforcement") | C3: 12 | D3: 90 | E3: 54 | F3: 36 | G3: Deal Pipeline Setup Guide Dealflow Concierge Diligence Analyst Evaluation Analyst First Look Analyst IC Prep Producer Integration Operator Legal & Compliance Desk Meeting Operator Origination Scout Pipeline Autopilot Sourcing Operator | H3: Analyze Deal Terms Audit LinkedIn Query Spend Capture Investment Management Handoff Capture Opportunity Intake Check Affinity Relationship Context Configure Companies House Public Register Preview Configure Origination Pipeline Coordinate Capital Call And Completion Create IC Memo Discover Companies House Candidates Discover GitHub Builder Signals Discover LinkedIn Founder Candidates Discover Reddit Builder Signals Discover X Founder Signals Draft Affinity Write-Back Proposals Draft Google Drive File Proposals Draft Notion Update Proposals Draft Slack Handoff Notifications Enrich Sourcing Candidate Explore Affinity Lists and Stages Explore Apify Origination Sources Explore Companies House Public Register Scope Explore Google Drive Sources Explore Harmonic Source Scopes Explore Notion Pages and Databases Explore Slack Channels for VC Context Generate Diligence Questions Generate Sourcing Digest Import Affinity Deal Pipeline Seed Ingest Manual Sourcing Tip Manage Closing Checklist Prepare Deal Flow Agenda Prepare IC Agenda Prepare Initial LinkedIn Reachout Prepare Lead Gen Packet Prepare Meeting Prepare Outreach Draft Queue Prepare Partner Review Pack Prepare Portfolio Onboarding Prepare Prospect Summary Prepare Second Reachout Email Prepare Team Review Pack Preview Affinity Pipeline Import Preview Apify Origination Results Preview Companies House Public Register Results Preview Google Drive Context Preview Harmonic Search Results Preview Notion Context Preview Slack Deal Context Promote Candidate to Deal Pipeline Record IC Decision Record LinkedIn Connection Attempt Request Founder Materials Review IC Memo Review Investment Documents Review Opportunity Status Review Outreach Outcome Review Portfolio Overlap Review Reddit Candidate Inbox Review Source Errors and Spend Review Term Sheet Review Unicorn Signature Run Commercial DD Run Commercial Evaluation Run Deal Fit Analysis Run Financial DD Run Financial Evaluation Run Founder Evaluation Run Investment Fit Screen Run Legal Diligence Run Opportunity Evaluation Run Team Evaluation Run Technical DD Run Technical Evaluation Run VC Sourcing Pipeline Score Sourcing Candidate Screen Active Sourcing Candidate Screen Founder-Connected Candidate Screen Identified Candidate Set Up Affinity for Deal Pipelines Set Up Apify for Origination Set Up Google Drive for Deal Pipelines Set Up Harmonic for Deal Pipelines Set Up Notion for Deal Pipelines Set Up Slack for Deal Pipelines Source Thesis Targets Summarize Meeting Records Sync Sourcing Candidate Track Term Sheet Negotiation Verify Conditions Precedent
B4: =HYPERLINK('Link Config'!$B$2&"plugins/vc/skills/vc-source-registry-and-state-management/SKILL.md","VC Source Registry & State Management") | C4: 1 | D4: 9 | E4: 8 | F4: 1 | G4: Sourcing Operator | H4: Audit LinkedIn Query Spend Discover Companies House Candidates Discover GitHub Builder Signals Discover LinkedIn Founder Candidates Discover Reddit Builder Signals Discover X Founder Signals Review Source Errors and Spend Run VC Sourcing Pipeline Sync Sourcing Candidate
B5: =HYPERLINK('Link Config'!$B$2&"plugins/vc/skills/red-flags-scanner/SKILL.md","Red Flags Scanner") | C5: 5 | D5: 8 | E5: 8 | F5: 0 | G5: Dealflow Concierge Diligence Analyst Evaluation Analyst First Look Analyst Legal & Compliance Desk | H5: Review Term Sheet Run Founder Evaluation Run Investment Fit Screen Run Legal Diligence Run Opportunity Evaluation Run Team Evaluation Run Technical DD Run Technical Evaluation
B6: =HYPERLINK('Link Config'!$B$2&"plugins/vc/skills/vc-task-and-next-step-generation/SKILL.md","VC Task & Next-Step Generation") | C6: 4 | D6: 7 | E6: 3 | F6: 4 | G6: IC Prep Producer Legal & Compliance Desk Meeting Operator Pipeline Autopilot | H6: Capture Investment Management Handoff Coordinate Capital Call And Completion Manage Closing Checklist Prepare Deal Flow Agenda Record IC Decision Review Opportunity Status Summarize Meeting Records
B7: =HYPERLINK('Link Config'!$B$2&"plugins/vc/skills/vc-outreach-draft-queue/SKILL.md","VC Outreach Draft Queue") | C7: 1 | D7: 6 | E7: 6 | F7: 0 | G7: Sourcing Operator | H7: Prepare Initial LinkedIn Reachout Prepare Outreach Draft Queue Prepare Second Reachout Email Record LinkedIn Connection Attempt Review Outreach Outcome Screen Founder-Connected Candidate
B8: =HYPERLINK('Link Config'!$B$2&"plugins/vc/skills/vc-sourcing-dedupe-and-novelty-check/SKILL.md","VC Sourcing Dedupe & Novelty Check") | C8: 1 | D8: 6 | E8: 6 | F8: 0 | G8: Sourcing Operator | H8: Enrich Sourcing Candidate Ingest Manual Sourcing Tip Review Reddit Candidate Inbox Score Sourcing Candidate Screen Identified Candidate Sync Sourcing Candidate
B9: =HYPERLINK('Link Config'!$B$2&"plugins/vc/skills/vc-sourcing-verdict-and-screening/SKILL.md","VC Sourcing Verdict & Screening") | C9: 1 | D9: 6 | E9: 6 | F9: 0 | G9: Sourcing Operator | H9: Review Unicorn Signature Run Deal Fit Analysis Score Sourcing Candidate Screen Active Sourcing Candidate Screen Founder-Connected Candidate Screen Identified Candidate
B10: =HYPERLINK('Link Config'!$B$2&"plugins/vc/skills/closing-coordination-and-cp-tracking/SKILL.md","Closing Coordination & CP Tracking") | C10: 1 | D10: 5 | E10: 5 | F10: 0 | G10: Legal & Compliance Desk | H10: Coordinate Capital Call And Completion Manage Closing Checklist Review Investment Documents Review Term Sheet Verify Conditions Precedent
B11: =HYPERLINK('Link Config'!$B$2&"plugins/vc/skills/founder-outreach-and-intro-paths/SKILL.md","Founder Outreach & Intro Paths") | C11: 2 | D11: 5 | E11: 5 | F11: 0 | G11: Origination Scout Sourcing Operator | H11: Prepare Initial LinkedIn Reachout Prepare Outreach Draft Queue Prepare Second Reachout Email Record LinkedIn Connection Attempt Source Thesis Targets
B12: =HYPERLINK('Link Config'!$B$2&"plugins/vc/skills/company-research-and-enrichment/SKILL.md","Company Research & Enrichment") | C12: 8 | D12: 4 | E12: 1 | F12: 3 | G12: Dealflow Concierge Diligence Analyst Evaluation Analyst First Look Analyst Meeting Operator Origination Scout Pipeline Autopilot Sourcing Operator | H12: Capture Opportunity Intake Prepare Lead Gen Packet Prepare Meeting Source Thesis Targets
B13: =HYPERLINK('Link Config'!$B$2&"plugins/vc/skills/ic-memo-assembly/SKILL.md","IC Memo Assembly") | C13: 2 | D13: 4 | E13: 4 | F13: 0 | G13: Diligence Analyst IC Prep Producer | H13: Create IC Memo Prepare Partner Review Pack Prepare Team Review Pack Review IC Memo
B14: =HYPERLINK('Link Config'!$B$2&"plugins/vc/skills/ic-risk-checklist-and-decision-log/SKILL.md","IC Risk Checklist & Decision Log") | C14: 1 | D14: 4 | E14: 4 | F14: 0 | G14: IC Prep Producer | H14: Create IC Memo Prepare IC Agenda Record IC Decision Review IC Memo
B15: =HYPERLINK('Link Config'!$B$2&"plugins/vc/skills/investment-screening-framework/SKILL.md","Investment Screening Framework") | C15: 5 | D15: 4 | E15: 4 | F15: 0 | G15: Dealflow Concierge First Look Analyst Meeting Operator Origination Scout Sourcing Operator | H15: Run Deal Fit Analysis Run Investment Fit Screen Screen Active Sourcing Candidate Screen Founder-Connected Candidate
B16: =HYPERLINK('Link Config'!$B$2&"plugins/vc/skills/deal-room-setup-and-source-ingestion/SKILL.md","Deal Pipeline Setup & Source Ingestion") | C16: 3 | D16: 3 | E16: 1 | F16: 2 | G16: Deal Pipeline Setup Guide Dealflow Concierge Sourcing Operator | H16: Capture Opportunity Intake Import Affinity Deal Pipeline Seed Promote Candidate to Deal Pipeline
B17: =HYPERLINK('Link Config'!$B$2&"plugins/vc/skills/meeting-prep-and-summary/SKILL.md","Meeting Prep & Summary") | C17: 2 | D17: 3 | E17: 1 | F17: 2 | G17: IC Prep Producer Meeting Operator | H17: Prepare IC Agenda Prepare Meeting Summarize Meeting Records
B18: =HYPERLINK('Link Config'!$B$2&"plugins/vc/skills/vc-affinity-sync-read/SKILL.md","VC Affinity Sync Read") | C18: 2 | D18: 3 | E18: 0 | F18: 3 | G18: Deal Pipeline Setup Guide Integration Operator | H18: Import Affinity Deal Pipeline Seed Preview Affinity Pipeline Import Set Up Affinity for Deal Pipelines
B19: =HYPERLINK('Link Config'!$B$2&"plugins/vc/skills/vc-companies-house-sourcing/SKILL.md","VC Companies House Sourcing") | C19: 2 | D19: 3 | E19: 1 | F19: 2 | G19: Integration Operator Sourcing Operator | H19: Configure Companies House Public Register Preview Discover Companies House Candidates Explore Companies House Public Register Scope
B20: =HYPERLINK('Link Config'!$B$2&"plugins/vc/skills/vc-notion-sync-write/SKILL.md","VC Notion Sync Write") | C20: 2 | D20: 3 | E20: 1 | F20: 2 | G20: Integration Operator Sourcing Operator | H20: Draft Notion Update Proposals Set Up Notion for Deal Pipelines Sync Sourcing Candidate
B21: =HYPERLINK('Link Config'!$B$2&"plugins/vc/skills/deal-terms-analysis/SKILL.md","Deal Terms Analysis") | C21: 1 | D21: 2 | E21: 2 | F21: 0 | G21: Legal & Compliance Desk | H21: Analyze Deal Terms Track Term Sheet Negotiation
B22: =HYPERLINK('Link Config'!$B$2&"plugins/vc/skills/investment-diligence-question-framework/SKILL.md","Investment Diligence Question Framework") | C22: 2 | D22: 2 | E22: 2 | F22: 0 | G22: Diligence Analyst Evaluation Analyst | H22: Generate Diligence Questions Run Opportunity Evaluation
B23: =HYPERLINK('Link Config'!$B$2&"plugins/vc/skills/legal-diligence-coordination/SKILL.md","Legal Diligence Coordination") | C23: 1 | D23: 2 | E23: 2 | F23: 0 | G23: Legal & Compliance Desk | H23: Review Investment Documents Run Legal Diligence
B24: =HYPERLINK('Link Config'!$B$2&"plugins/vc/skills/pitch-deck-explainer/SKILL.md","Pitch Deck Explainer") | C24: 2 | D24: 2 | E24: 0 | F24: 2 | G24: Dealflow Concierge Meeting Operator | H24: Capture Opportunity Intake Prepare Meeting
B25: =HYPERLINK('Link Config'!$B$2&"plugins/vc/skills/team-and-hiring-assessment/SKILL.md","Team & Hiring Assessment") | C25: 1 | D25: 2 | E25: 2 | F25: 0 | G25: Diligence Analyst | H25: Run Founder Evaluation Run Technical DD
B26: =HYPERLINK('Link Config'!$B$2&"plugins/vc/skills/vc-affinity-discovery/SKILL.md","VC Affinity Discovery") | C26: 2 | D26: 2 | E26: 0 | F26: 2 | G26: Deal Pipeline Setup Guide Integration Operator | H26: Explore Affinity Lists and Stages Set Up Affinity for Deal Pipelines
B27: =HYPERLINK('Link Config'!$B$2&"plugins/vc/skills/vc-affinity-sync-write/SKILL.md","VC Affinity Sync Write") | C27: 2 | D27: 2 | E27: 0 | F27: 2 | G27: Deal Pipeline Setup Guide Integration Operator | H27: Draft Affinity Write-Back Proposals Set Up Affinity for Deal Pipelines
B28: =HYPERLINK('Link Config'!$B$2&"plugins/vc/skills/vc-apify-discovery/SKILL.md","VC Apify Discovery") | C28: 1 | D28: 2 | E28: 0 | F28: 2 | G28: Integration Operator | H28: Explore Apify Origination Sources Set Up Apify for Origination
B29: =HYPERLINK('Link Config'!$B$2&"plugins/vc/skills/vc-apify-sync-read/SKILL.md","VC Apify Sync Read") | C29: 1 | D29: 2 | E29: 0 | F29: 2 | G29: Integration Operator | H29: Preview Apify Origination Results Set Up Apify for Origination
B30: =HYPERLINK('Link Config'!$B$2&"plugins/vc/skills/vc-companies-house-sync-read/SKILL.md","VC Companies House Sync Read") | C30: 1 | D30: 2 | E30: 0 | F30: 2 | G30: Integration Operator | H30: Configure Companies House Public Register Preview Preview Companies House Public Register Results
B31: =HYPERLINK('Link Config'!$B$2&"plugins/vc/skills/vc-google-drive-discovery/SKILL.md","VC Google Drive Discovery") | C31: 1 | D31: 2 | E31: 0 | F31: 2 | G31: Integration Operator | H31: Explore Google Drive Sources Set Up Google Drive for Deal Pipelines
B32: =HYPERLINK('Link Config'!$B$2&"plugins/vc/skills/vc-google-drive-sync-read/SKILL.md","VC Google Drive Sync Read") | C32: 1 | D32: 2 | E32: 0 | F32: 2 | G32: Integration Operator | H32: Preview Google Drive Context Set Up Google Drive for Deal Pipelines
B33: =HYPERLINK('Link Config'!$B$2&"plugins/vc/skills/vc-google-drive-sync-write/SKILL.md","VC Google Drive Sync Write") | C33: 1 | D33: 2 | E33: 0 | F33: 2 | G33: Integration Operator | H33: Draft Google Drive File Proposals Set Up Google Drive for Deal Pipelines
B34: =HYPERLINK('Link Config'!$B$2&"plugins/vc/skills/vc-harmonic-discovery/SKILL.md","VC Harmonic Discovery") | C34: 1 | D34: 2 | E34: 0 | F34: 2 | G34: Integration Operator | H34: Explore Harmonic Source Scopes Set Up Harmonic for Deal Pipelines
B35: =HYPERLINK('Link Config'!$B$2&"plugins/vc/skills/vc-harmonic-sync-read/SKILL.md","VC Harmonic Sync Read") | C35: 1 | D35: 2 | E35: 0 | F35: 2 | G35: Integration Operator | H35: Preview Harmonic Search Results Set Up Harmonic for Deal Pipelines
B36: =HYPERLINK('Link Config'!$B$2&"plugins/vc/skills/vc-notion-discovery/SKILL.md","VC Notion Discovery") | C36: 1 | D36: 2 | E36: 0 | F36: 2 | G36: Integration Operator | H36: Explore Notion Pages and Databases Set Up Notion for Deal Pipelines
B37: =HYPERLINK('Link Config'!$B$2&"plugins/vc/skills/vc-notion-sync-read/SKILL.md","VC Notion Sync Read") | C37: 1 | D37: 2 | E37: 0 | F37: 2 | G37: Integration Operator | H37: Preview Notion Context Set Up Notion for Deal Pipelines
B38: =HYPERLINK('Link Config'!$B$2&"plugins/vc/skills/vc-origination-deal-room-promotion/SKILL.md","Origination Deal Pipeline Promotion") | C38: 1 | D38: 2 | E38: 2 | F38: 0 | G38: Sourcing Operator | H38: Promote Candidate to Deal Pipeline Review Outreach Outcome
B39: =HYPERLINK('Link Config'!$B$2&"plugins/vc/skills/vc-origination-ic-summary-preparation/SKILL.md","Origination Prospect Summary Preparation") | C39: 1 | D39: 2 | E39: 2 | F39: 0 | G39: Sourcing Operator | H39: Prepare Prospect Summary Review Unicorn Signature
B40: =HYPERLINK('Link Config'!$B$2&"plugins/vc/skills/vc-origination-pipeline-orchestration/SKILL.md","Origination Pipeline Orchestration") | C40: 1 | D40: 2 | E40: 1 | F40: 1 | G40: Sourcing Operator | H40: Configure Origination Pipeline Run VC Sourcing Pipeline
B41: =HYPERLINK('Link Config'!$B$2&"plugins/vc/skills/vc-relationship-context-check/SKILL.md","VC Relationship Context Check") | C41: 1 | D41: 2 | E41: 2 | F41: 0 | G41: Sourcing Operator | H41: Check Affinity Relationship Context Review Portfolio Overlap
B42: =HYPERLINK('Link Config'!$B$2&"plugins/vc/skills/vc-slack-discovery/SKILL.md","VC Slack Discovery") | C42: 1 | D42: 2 | E42: 0 | F42: 2 | G42: Integration Operator | H42: Explore Slack Channels for VC Context Set Up Slack for Deal Pipelines
B43: =HYPERLINK('Link Config'!$B$2&"plugins/vc/skills/vc-slack-sync-read/SKILL.md","VC Slack Sync Read") | C43: 1 | D43: 2 | E43: 0 | F43: 2 | G43: Integration Operator | H43: Preview Slack Deal Context Set Up Slack for Deal Pipelines
B44: =HYPERLINK('Link Config'!$B$2&"plugins/vc/skills/vc-slack-sync-write/SKILL.md","VC Slack Sync Write") | C44: 1 | D44: 2 | E44: 0 | F44: 2 | G44: Integration Operator | H44: Draft Slack Handoff Notifications Set Up Slack for Deal Pipelines
B45: =HYPERLINK('Link Config'!$B$2&"plugins/vc/skills/commercial-diligence-workstream/SKILL.md","Commercial Diligence Workstream") | C45: 1 | D45: 1 | E45: 1 | F45: 0 | G45: Diligence Analyst | H45: Run Commercial DD
B46: =HYPERLINK('Link Config'!$B$2&"plugins/vc/skills/commercial-evaluation-and-market-risk/SKILL.md","Commercial Evaluation & Market Risk") | C46: 1 | D46: 1 | E46: 1 | F46: 0 | G46: Evaluation Analyst | H46: Run Commercial Evaluation
B47: =HYPERLINK('Link Config'!$B$2&"plugins/vc/skills/financial-diligence-workstream/SKILL.md","Financial Diligence Workstream") | C47: 1 | D47: 1 | E47: 1 | F47: 0 | G47: Diligence Analyst | H47: Run Financial DD
B48: =HYPERLINK('Link Config'!$B$2&"plugins/vc/skills/financial-evaluation-and-financing-risk/SKILL.md","Financial Evaluation & Financing Risk") | C48: 1 | D48: 1 | E48: 1 | F48: 0 | G48: Evaluation Analyst | H48: Run Financial Evaluation
B49: =HYPERLINK('Link Config'!$B$2&"plugins/vc/skills/founder-evaluation-and-reference-checking/SKILL.md","Founder Evaluation & Reference Checking") | C49: 1 | D49: 1 | E49: 1 | F49: 0 | G49: Diligence Analyst | H49: Run Founder Evaluation
B50: =HYPERLINK('Link Config'!$B$2&"plugins/vc/skills/founder-materials-request/SKILL.md","Founder Materials Request") | C50: 1 | D50: 1 | E50: 0 | F50: 1 | G50: Dealflow Concierge | H50: Request Founder Materials
B51: =HYPERLINK('Link Config'!$B$2&"plugins/vc/skills/portfolio-onboarding-and-100-day-plan/SKILL.md","Portfolio Onboarding & 100-Day Plan") | C51: 1 | D51: 1 | E51: 1 | F51: 0 | G51: Legal & Compliance Desk | H51: Prepare Portfolio Onboarding
B52: =HYPERLINK('Link Config'!$B$2&"plugins/vc/skills/team-evaluation-and-founder-risk/SKILL.md","Team Evaluation & Founder Risk") | C52: 1 | D52: 1 | E52: 1 | F52: 0 | G52: Evaluation Analyst | H52: Run Team Evaluation
B53: =HYPERLINK('Link Config'!$B$2&"plugins/vc/skills/technical-diligence-workstream/SKILL.md","Technical Diligence Workstream") | C53: 1 | D53: 1 | E53: 1 | F53: 0 | G53: Diligence Analyst | H53: Run Technical DD
B54: =HYPERLINK('Link Config'!$B$2&"plugins/vc/skills/technical-evaluation-and-product-risk/SKILL.md","Technical Evaluation & Product Risk") | C54: 1 | D54: 1 | E54: 1 | F54: 0 | G54: Evaluation Analyst | H54: Run Technical Evaluation
B55: =HYPERLINK('Link Config'!$B$2&"plugins/vc/skills/term-sheet-negotiation-brief/SKILL.md","Term Sheet Negotiation Brief") | C55: 1 | D55: 1 | E55: 1 | F55: 0 | G55: Legal & Compliance Desk | H55: Track Term Sheet Negotiation
B56: =HYPERLINK('Link Config'!$B$2&"plugins/vc/skills/vc-affinity-deal-room-import/SKILL.md","VC Affinity Deal Pipeline Import") | C56: 1 | D56: 1 | E56: 0 | F56: 1 | G56: Deal Pipeline Setup Guide | H56: Import Affinity Deal Pipeline Seed
B57: =HYPERLINK('Link Config'!$B$2&"plugins/vc/skills/vc-apify-linkedin-founder-discovery/SKILL.md","VC Apify LinkedIn Founder Discovery") | C57: 1 | D57: 1 | E57: 1 | F57: 0 | G57: Sourcing Operator | H57: Discover LinkedIn Founder Candidates
B58: =HYPERLINK('Link Config'!$B$2&"plugins/vc/skills/vc-apify-x-founder-discovery/SKILL.md","VC Apify X Founder Discovery") | C58: 1 | D58: 1 | E58: 1 | F58: 0 | G58: Sourcing Operator | H58: Discover X Founder Signals
B59: =HYPERLINK('Link Config'!$B$2&"plugins/vc/skills/vc-github-builder-signal-discovery/SKILL.md","VC GitHub Builder Signal Discovery") | C59: 1 | D59: 1 | E59: 1 | F59: 0 | G59: Sourcing Operator | H59: Discover GitHub Builder Signals
B60: =HYPERLINK('Link Config'!$B$2&"plugins/vc/skills/vc-linkedin-query-spend-audit/SKILL.md","VC LinkedIn Query Spend Audit") | C60: 1 | D60: 1 | E60: 1 | F60: 0 | G60: Sourcing Operator | H60: Audit LinkedIn Query Spend
B61: =HYPERLINK('Link Config'!$B$2&"plugins/vc/skills/vc-manual-tip-ingestion/SKILL.md","VC Manual Tip Ingestion") | C61: 1 | D61: 1 | E61: 1 | F61: 0 | G61: Sourcing Operator | H61: Ingest Manual Sourcing Tip
B62: =HYPERLINK('Link Config'!$B$2&"plugins/vc/skills/vc-portfolio-overlap-review/SKILL.md","VC Portfolio Overlap Review") | C62: 1 | D62: 1 | E62: 1 | F62: 0 | G62: Sourcing Operator | H62: Review Portfolio Overlap
B63: =HYPERLINK('Link Config'!$B$2&"plugins/vc/skills/vc-reddit-builder-signal-discovery/SKILL.md","VC Reddit Builder Signal Discovery") | C63: 1 | D63: 1 | E63: 1 | F63: 0 | G63: Sourcing Operator | H63: Discover Reddit Builder Signals
B64: =HYPERLINK('Link Config'!$B$2&"plugins/vc/skills/vc-reddit-inbox-approval/SKILL.md","VC Reddit Inbox Approval") | C64: 1 | D64: 1 | E64: 1 | F64: 0 | G64: Sourcing Operator | H64: Review Reddit Candidate Inbox
B65: =HYPERLINK('Link Config'!$B$2&"plugins/vc/skills/vc-source-error-and-spend-audit/SKILL.md","VC Source Error & Spend Audit") | C65: 1 | D65: 1 | E65: 0 | F65: 1 | G65: Sourcing Operator | H65: Review Source Errors and Spend
B66: =HYPERLINK('Link Config'!$B$2&"plugins/vc/skills/vc-sourcing-candidate-enrichment/SKILL.md","VC Sourcing Candidate Enrichment") | C66: 1 | D66: 1 | E66: 1 | F66: 0 | G66: Sourcing Operator | H66: Enrich Sourcing Candidate
B67: =HYPERLINK('Link Config'!$B$2&"plugins/vc/skills/vc-sourcing-digest-generation/SKILL.md","VC Sourcing Digest Generation") | C67: 1 | D67: 1 | E67: 1 | F67: 0 | G67: Sourcing Operator | H67: Generate Sourcing Digest

Sheet Document Catalog
A1: Document | B1: Type | C1: Projects | D1: Description | E1: Related Tasks
A2: Linked document | B2: Document Type | C2: Supported Project Types | D2: Description | E2: Related Task Slugs
A3: =HYPERLINK('Link Config'!$B$2&"plugins/vc/alludium/documents/shared/investment-screening-framework.md","Investment Screening Framework") | B3: methodology | C3: vc_deal_room vc_origination_pipeline | D3: Reusable first-look scorecard methodology for deciding whether a venture opportunity deserves deeper work. | E3: run-investment-screen score-sourcing-candidates screen-active-sourcing-candidates screen-inbound-opportunity
A4: =HYPERLINK('Link Config'!$B$2&"plugins/vc/alludium/documents/shared/investment-diligence-question-framework.md","Investment Diligence Question Framework") | B4: methodology | C4: vc_deal_room vc_origination_pipeline vc_investment_management | D4: Structured diligence question-bank methodology for converting knowns, unknowns, and risks into workstream questions. | E4: generate-diligence-questions run-commercial-dd run-financial-dd run-technical-dd
A5: =HYPERLINK('Link Config'!$B$2&"plugins/vc/alludium/documents/shared/opportunity-evaluation-framework.md","Opportunity Evaluation Framework") | B5: methodology | C5: vc_deal_room | D5: Evidence-led post-screening opportunity evaluation methodology with scoring, thesis tension, gating risk, and meeting/data-room planning standards. | E5: create-ic-memo generate-diligence-questions prepare-partner-review-pack prepare-team-review-pack review-opportunity-status review-ic-memo run-follow-up-evaluation run-team-evaluation run-financial-evaluation run-technical-evaluation run-commercial-evaluation
A6: =HYPERLINK('Link Config'!$B$2&"plugins/vc/alludium/documents/shared/evaluation-workstream-guide.md","Evaluation Workstream Guide") | B6: methodology | C6: vc_deal_room | D6: Lightweight commercial, technical, financial, and team evaluation guidance for post-screening work before formal diligence. | E6: create-ic-memo generate-diligence-questions prepare-partner-review-pack prepare-team-review-pack review-ic-memo review-opportunity-status run-follow-up-evaluation run-team-evaluation run-financial-evaluation run-technical-evaluation run-commercial-evaluation
A7: =HYPERLINK('Link Config'!$B$2&"plugins/vc/alludium/documents/deal-room/commercial-evaluation-guide.md","Commercial Evaluation Guide") | B7: methodology | C7: vc_deal_room | D7: Lightweight commercial evaluation guidance for market, customer, GTM, pricing, and competition hypotheses. | E7: generate-diligence-questions run-follow-up-evaluation run-commercial-evaluation
A8: =HYPERLINK('Link Config'!$B$2&"plugins/vc/alludium/documents/deal-room/technical-evaluation-guide.md","Technical Evaluation Guide") | B8: methodology | C8: vc_deal_room | D8: Lightweight technical evaluation guidance for product, architecture, technical edge, IP, data, and roadmap hypotheses. | E8: generate-diligence-questions run-follow-up-evaluation run-technical-evaluation
A9: =HYPERLINK('Link Config'!$B$2&"plugins/vc/alludium/documents/deal-room/financial-evaluation-guide.md","Financial Evaluation Guide") | B9: methodology | C9: vc_deal_room | D9: Lightweight financial evaluation guidance for forecast plausibility, burn, runway, use of funds, valuation, ownership, and financing risk. | E9: generate-diligence-questions run-follow-up-evaluation run-financial-evaluation
A10: =HYPERLINK('Link Config'!$B$2&"plugins/vc/alludium/documents/shared/evidence-citation-style-guide.md","Evidence And Citation Style Guide") | B10: style_guide | C10: vc_deal_room vc_origination_pipeline vc_investment_management | D10: Pack-level style guide for citations, assumptions, source confidence, and claim hygiene across VC documents. | E10: create-ic-memo generate-diligence-questions prepare-partner-review-pack prepare-sourcing-ic-summary prepare-team-review-pack record-ic-decision run-commercial-dd run-financial-dd run-founder-evaluation run-investment-screen run-sourcing-pipeline run-technical-dd screen-inbound-opportunity run-commercial-evaluation run-technical-evaluation run-financial-evaluation run-team-evaluation
A11: =HYPERLINK('Link Config'!$B$2&"plugins/vc/alludium/documents/shared/template-use-guidance.md","Template Use Guidance") | B11: sop | C11: vc_deal_room vc_origination_pipeline vc_investment_management | D11: Operating guidance for applying VC document templates as adaptable scaffolds without producing generic filler. | E11: audit-linkedin-query-spend configure-origination-pipeline create-ic-memo generate-diligence-questions generate-sourcing-digest manage-closing-checklist prepare-ic-agenda prepare-initial-call prepare-lead-gen-packet prepare-outreach-draft-queue prepare-partner-review-pack prepare-portfolio-onboarding prepare-sourcing-ic-summary prepare-team-review-pack promote-candidate-to-deal-room record-ic-decision request-founder-materials review-ic-memo review-source-errors-and-spend review-term-sheet run-commercial-dd run-financial-dd run-follow-up-evaluation run-team-evaluation run-financial-evaluation run-technical-evaluation run-commercial-evaluation run-founder-evaluation run-investment-screen run-sourcing-pipeline run-technical-dd score-sourcing-candidates screen-active-sourcing-candidates screen-inbound-opportunity source-thesis-targets summarize-initial-call verify-conditions-precedent
A12: =HYPERLINK('Link Config'!$B$2&"plugins/vc/alludium/documents/shared/file-naming-source-index-sop.md","File Naming And Source Index SOP") | B12: sop | C12: vc_deal_room vc_origination_pipeline vc_investment_management | D12: Operating convention for naming files, tracking source provenance, and maintaining a compact source index. | E12: request-founder-materials run-sourcing-pipeline sync-sourcing-candidates
A13: =HYPERLINK('Link Config'!$B$2&"plugins/vc/alludium/documents/deal-room/deal-room-sop.md","Deal Pipeline Operating SOP") | B13: sop | C13: vc_deal_room | D13: End-to-end Deal Pipeline operating method from intake through closing and portfolio handoff. | E13: prepare-partner-review-pack prepare-team-review-pack review-opportunity-status
A14: =HYPERLINK('Link Config'!$B$2&"plugins/vc/alludium/documents/deal-room/founder-materials-request-template.md","Founder Materials Request Template") | B14: template | C14: vc_deal_room | D14: Reusable founder request template for source materials, financials, customer evidence, technical context, and legal basics. | E14: request-founder-materials
A15: =HYPERLINK('Link Config'!$B$2&"plugins/vc/alludium/documents/deal-room/thesis-target-list-template.md","Thesis Target List Template") | B15: template | C15: vc_origination_pipeline | D15: Reusable target-list format for thesis-led sourcing and warm-intro planning. | E15: source-thesis-targets
A16: =HYPERLINK('Link Config'!$B$2&"plugins/vc/alludium/documents/deal-room/lead-generation-packet-template.md","Lead Generation Packet Template") | B16: template | C16: vc_origination_pipeline | D16: Reusable management-level packet for thesis-led lead generation reviews. | E16: prepare-lead-gen-packet
A17: =HYPERLINK('Link Config'!$B$2&"plugins/vc/alludium/documents/deal-room/initial-call-brief-template.md","Initial Call Brief Template") | B17: template | C17: vc_deal_room | D17: Reusable pre-call brief for first founder or management meetings. | E17: prepare-initial-call
A18: =HYPERLINK('Link Config'!$B$2&"plugins/vc/alludium/documents/deal-room/customer-insights-summary-template.md","Customer Insights Summary Template") | B18: template | C18: vc_deal_room | D18: Reusable meeting-record summary for customer, founder, and diligence call evidence. | E18: summarize-initial-call
A19: =HYPERLINK('Link Config'!$B$2&"plugins/vc/alludium/documents/deal-room/follow-up-evaluation-template.md","Opportunity Evaluation Template") | B19: template | C19: vc_deal_room | D19: Reusable deeper opportunity evaluation after investment screening and early evidence collection. | E19: run-follow-up-evaluation
A20: =HYPERLINK('Link Config'!$B$2&"plugins/vc/alludium/documents/deal-room/team-evaluation-template.md","Team Evaluation Template") | B20: template | C20: vc_deal_room | D20: Output template for lightweight team and founder evaluation before formal diligence. | E20: run-team-evaluation
A21: =HYPERLINK('Link Config'!$B$2&"plugins/vc/alludium/documents/deal-room/financial-evaluation-template.md","Financial Evaluation Template") | B21: template | C21: vc_deal_room | D21: Output template for lightweight financial and financing evaluation before formal diligence. | E21: run-financial-evaluation
A22: =HYPERLINK('Link Config'!$B$2&"plugins/vc/alludium/documents/deal-room/technical-evaluation-template.md","Technical Evaluation Template") | B22: template | C22: vc_deal_room | D22: Output template for lightweight technical and product evaluation before formal diligence. | E22: run-technical-evaluation
A23: =HYPERLINK('Link Config'!$B$2&"plugins/vc/alludium/documents/deal-room/commercial-evaluation-template.md","Commercial Evaluation Template") | B23: template | C23: vc_deal_room | D23: Output template for lightweight commercial evaluation before formal diligence. | E23: run-commercial-evaluation
A24: =HYPERLINK('Link Config'!$B$2&"plugins/vc/alludium/documents/deal-room/investment-memo-template.md","Investment Memo Template") | B24: template | C24: vc_deal_room | D24: Reusable IC investment memo structure with thesis, evidence, risks, valuation, diligence, and decision ask. | E24: create-ic-memo review-ic-memo
A25: =HYPERLINK('Link Config'!$B$2&"plugins/vc/alludium/documents/deal-room/ic-agenda-template.md","IC Agenda Template") | B25: template | C25: vc_deal_room | D25: Reusable investment committee agenda for sequencing discussion, open questions, decision items, and pre-reads. | E25: prepare-ic-agenda
A26: =HYPERLINK('Link Config'!$B$2&"plugins/vc/alludium/documents/deal-room/ic-decision-record-template.md","IC Decision Record Template") | B26: template | C26: vc_deal_room | D26: Reusable decision record for approvals, conditions, dissent, follow-ups, and evidence references. | E26: record-ic-decision
A27: =HYPERLINK('Link Config'!$B$2&"plugins/vc/alludium/documents/deal-room/diligence-report-template.md","Diligence Report Template") | B27: template | C27: vc_investment_management | D27: Reusable diligence report structure for commercial, technical, financial, founder, and legal workstreams. | E27: run-commercial-dd run-financial-dd run-founder-evaluation run-technical-dd
A28: =HYPERLINK('Link Config'!$B$2&"plugins/vc/alludium/documents/deal-room/formal-diligence-workstream-guide.md","Formal Diligence Workstream Guide") | B28: methodology | C28: vc_deal_room vc_investment_management | D28: Verification-oriented diligence workstream methodology for commercial, financial, technical, founder/team, legal, market, terms, and exit review. | E28: create-ic-memo generate-diligence-questions prepare-partner-review-pack prepare-team-review-pack review-ic-memo run-commercial-dd run-financial-dd run-founder-evaluation run-legal-diligence run-technical-dd
A29: =HYPERLINK('Link Config'!$B$2&"plugins/vc/alludium/documents/deal-room/formal-diligence-checklist.md","Formal Diligence Checklist") | B29: checklist | C29: vc_deal_room vc_investment_management | D29: Full formal diligence checklist covering leadership, technical, commercial, market, financial, legal, deal-terms, exit, and company-structure workstreams. | E29: create-ic-memo generate-diligence-questions prepare-partner-review-pack prepare-team-review-pack review-ic-memo run-commercial-dd run-financial-dd run-founder-evaluation run-legal-diligence run-technical-dd
A30: =HYPERLINK('Link Config'!$B$2&"plugins/vc/alludium/documents/deal-room/review-pack-checklist.md","Review Pack Checklist") | B30: checklist | C30: vc_deal_room | D30: Checklist for team review and partner review packs before escalation to IC materials. | E30: prepare-partner-review-pack prepare-team-review-pack
A31: =HYPERLINK('Link Config'!$B$2&"plugins/vc/alludium/documents/deal-room/ic-memo-review-template.md","IC Memo Review Template") | B31: template | C31: vc_deal_room | D31: Reusable review format for checking IC memo readiness, gaps, and required changes. | E31: review-ic-memo
A32: =HYPERLINK('Link Config'!$B$2&"plugins/vc/alludium/documents/deal-room/deal-terms-analysis-template.md","Deal Terms Analysis Template") | B32: template | C32: vc_deal_room | D32: Reusable commercial review format for valuation, ownership, dilution, ESOP, and round construction analysis. | E32: analyze-deal-terms
A33: =HYPERLINK('Link Config'!$B$2&"plugins/vc/alludium/documents/deal-room/term-sheet-negotiation-brief-template.md","Term Sheet Negotiation Brief Template") | B33: template | C33: vc_deal_room | D33: Reusable internal brief for open terms, give/get options, counsel questions, and approval points. | E33: track-term-sheet-negotiation
A34: =HYPERLINK('Link Config'!$B$2&"plugins/vc/alludium/documents/deal-room/term-sheet-review-template.md","Term Sheet Review Template") | B34: template | C34: vc_deal_room | D34: Reusable business review format for term-sheet deviations, red flags, and counsel questions. | E34: review-term-sheet
A35: =HYPERLINK('Link Config'!$B$2&"plugins/vc/alludium/documents/deal-room/legal-diligence-tracker-template.md","Legal Diligence Tracker Template") | B35: template | C35: vc_investment_management | D35: Reusable tracker for legal document indexing, issue registers, counsel questions, and showstopper-risk review support. | E35: run-legal-diligence
A36: =HYPERLINK('Link Config'!$B$2&"plugins/vc/alludium/documents/deal-room/legal-diligence-guide.md","Legal Diligence Guide") | B36: methodology | C36: vc_investment_management | D36: Legal diligence guidance for document indexing, issue tracking, counsel questions, and legal-risk escalation without legal advice. | E36: run-legal-diligence review-investment-documents manage-closing-checklist verify-conditions-precedent
A37: =HYPERLINK('Link Config'!$B$2&"plugins/vc/alludium/documents/deal-room/investment-document-review-template.md","Investment Document Review Template") | B37: template | C37: vc_investment_management | D37: Reusable review-support format for mapping investment documents back to approved terms and open counsel issues. | E37: review-investment-documents
A38: =HYPERLINK('Link Config'!$B$2&"plugins/vc/alludium/documents/deal-room/closing-checklist.md","Closing Checklist") | B38: checklist | C38: vc_investment_management | D38: Checklist for legal, finance, operational, and onboarding readiness before signing and completion. | E38: manage-closing-checklist
A39: =HYPERLINK('Link Config'!$B$2&"plugins/vc/alludium/documents/deal-room/conditions-precedent-tracker-template.md","Conditions Precedent Tracker Template") | B39: template | C39: vc_investment_management | D39: Reusable tracker for condition, owner, evidence, blocker, counsel review, and completion status. | E39: verify-conditions-precedent
A40: =HYPERLINK('Link Config'!$B$2&"plugins/vc/alludium/documents/deal-room/completion-tracker-template.md","Completion Tracker Template") | B40: template | C40: vc_investment_management | D40: Reusable tracker for capital call status, funds transfer readiness, completion evidence, and portfolio handoff triggers. | E40: coordinate-capital-call-and-completion
A41: =HYPERLINK('Link Config'!$B$2&"plugins/vc/alludium/documents/deal-room/portfolio-onboarding-plan-template.md","Portfolio Onboarding Plan Template") | B41: template | C41: vc_investment_management | D41: Reusable post-close onboarding plan covering owners, first 100 days, reporting, board setup, and operating cadence. | E41: prepare-portfolio-onboarding
A42: =HYPERLINK('Link Config'!$B$2&"plugins/vc/alludium/documents/origination/origination-pipeline-sop.md","Origination Pipeline Operating SOP") | B42: sop | C42: vc_origination_pipeline | D42: Operating method for standing venture sourcing pipelines from source configuration through promotion packages. | E42: configure-origination-pipeline promote-candidate-to-deal-room run-sourcing-pipeline
A43: =HYPERLINK('Link Config'!$B$2&"plugins/vc/alludium/documents/origination/origination-source-strategy-guide.md","Origination Source Strategy Guide") | B43: methodology | C43: vc_deal_room vc_origination_pipeline | D43: Source strategy, source provenance, source quality, and promotion-readiness methodology for venture origination pipelines. | E43: configure-origination-pipeline prepare-lead-gen-packet prepare-sourcing-ic-summary promote-candidate-to-deal-room run-sourcing-pipeline score-sourcing-candidates screen-active-sourcing-candidates source-thesis-targets
A44: =HYPERLINK('Link Config'!$B$2&"plugins/vc/alludium/documents/origination/source-registry-template.md","Source Registry Template") | B44: template | C44: vc_origination_pipeline | D44: Reusable registry for source keys, scopes, owners, credential state, budgets, cadence, and review policy. | E44: configure-origination-pipeline run-sourcing-pipeline
A45: =HYPERLINK('Link Config'!$B$2&"plugins/vc/alludium/documents/origination/candidate-batch-template.md","Candidate Batch Template") | B45: template | C45: vc_origination_pipeline | D45: Reusable batch review template for sourced companies, evidence, dedupe state, fit scores, and next actions. | E45: enrich-sourcing-candidates run-sourcing-pipeline score-sourcing-candidates
A46: =HYPERLINK('Link Config'!$B$2&"plugins/vc/alludium/documents/origination/sourcing-scoring-rubric.md","Sourcing Scoring Rubric") | B46: methodology | C46: vc_origination_pipeline | D46: Reusable scoring rubric for sourced candidate fit, evidence quality, novelty, timing, and promotion readiness. | E46: score-sourcing-candidates screen-active-sourcing-candidates
A47: =HYPERLINK('Link Config'!$B$2&"plugins/vc/alludium/documents/origination/source-health-review-checklist.md","Source Health Review Checklist") | B47: checklist | C47: vc_origination_pipeline | D47: Checklist for reviewing source freshness, error rates, coverage drift, duplication, and review queue quality. | E47: review-source-errors-and-spend
A48: =HYPERLINK('Link Config'!$B$2&"plugins/vc/alludium/documents/origination/paid-source-spend-audit-checklist.md","Paid Source Spend Audit Checklist") | B48: checklist | C48: vc_origination_pipeline | D48: Checklist for paid-source budgets, query cost, usage spikes, result quality, and disabled-source policy. | E48: audit-linkedin-query-spend review-source-errors-and-spend
A49: =HYPERLINK('Link Config'!$B$2&"plugins/vc/alludium/documents/origination/sourcing-digest-template.md","Sourcing Digest Template") | B49: template | C49: vc_origination_pipeline | D49: Reusable sourcing digest format for new candidates, changes, source performance, decisions, and follow-ups. | E49: generate-sourcing-digest
A50: =HYPERLINK('Link Config'!$B$2&"plugins/vc/alludium/documents/origination/outreach-queue-template.md","Outreach Queue Template") | B50: template | C50: vc_origination_pipeline | D50: Reusable outreach queue template for candidate priority, reason to reach out, channel, owner, and draft status. | E50: prepare-outreach-draft-queue
A51: =HYPERLINK('Link Config'!$B$2&"plugins/vc/alludium/documents/origination/promotion-package-template.md","Promotion Package Template") | B51: template | C51: vc_origination_pipeline | D51: Reusable promotion package for turning a sourced candidate into a Deal Pipeline creation or update recommendation. | E51: prepare-sourcing-ic-summary promote-candidate-to-deal-room
A52: =HYPERLINK('Link Config'!$B$2&"plugins/vc/alludium/documents/origination/sourcing-ic-summary-template.md","Prospect Summary Template") | B52: template | C52: vc_origination_pipeline | D52: Reusable prospect-level sourcing summary for one prioritized candidate before outreach or Deal Pipeline promotion. | E52: prepare-sourcing-ic-summary
A53: =HYPERLINK('Link Config'!$B$2&"plugins/vc/alludium/documents/origination/dedupe-novelty-policy.md","Dedupe And Novelty Policy") | B53: policy | C53: vc_origination_pipeline | D53: Policy for matching sourced candidates to existing opportunities, relationships, and prior rejects before promotion. | E53: screen-active-sourcing-candidates
A54: =HYPERLINK('Link Config'!$B$2&"plugins/vc/alludium/documents/origination/apify-source-setup-checklist.md","Apify Source Setup Checklist") | B54: checklist | C54: vc_origination_pipeline | D54: Source-specific setup checklist for Apify actor allowlists, inputs, spend controls, and preview policy. | E54: apify-discovery apify-setup apify-sync-read
A55: =HYPERLINK('Link Config'!$B$2&"plugins/vc/alludium/documents/origination/companies-house-source-setup-checklist.md","Companies House Source Setup Checklist") | B55: checklist | C55: vc_origination_pipeline | D55: Source-specific setup checklist for public-register discovery scope, region policy, and reviewed read-preview. | E55: companies-house-discovery companies-house-setup companies-house-sync-read

Sheet Task Skill Links
A1: Project | B1: Stage | C1: Task | D1: Skill
A2: Project Type | B2: Stage / Pseudo-stage | C2: Linked task | D2: Linked skill
A3: Deal Pipeline | B3: Setup | C3: =HYPERLINK('Link Config'!$B$2&"plugins/vc/tasks/screen-inbound-opportunity.md","Capture Opportunity Intake") | D3: =HYPERLINK('Link Config'!$B$2&"plugins/vc/skills/deal-room-setup-and-source-ingestion/SKILL.md","Deal Pipeline Setup & Source Ingestion")
A4: Deal Pipeline | B4: Setup | C4: =HYPERLINK('Link Config'!$B$2&"plugins/vc/tasks/screen-inbound-opportunity.md","Capture Opportunity Intake") | D4: =HYPERLINK('Link Config'!$B$2&"plugins/vc/skills/company-research-and-enrichment/SKILL.md","Company Research & Enrichment")
A5: Deal Pipeline | B5: Setup | C5: =HYPERLINK('Link Config'!$B$2&"plugins/vc/tasks/screen-inbound-opportunity.md","Capture Opportunity Intake") | D5: =HYPERLINK('Link Config'!$B$2&"plugins/vc/skills/citation-enforcement/SKILL.md","Citation Enforcement")
A6: Deal Pipeline | B6: Setup | C6: =HYPERLINK('Link Config'!$B$2&"plugins/vc/tasks/screen-inbound-opportunity.md","Capture Opportunity Intake") | D6: =HYPERLINK('Link Config'!$B$2&"plugins/vc/skills/pitch-deck-explainer/SKILL.md","Pitch Deck Explainer")
A7: Deal Pipeline | B7: Setup | C7: =HYPERLINK('Link Config'!$B$2&"plugins/vc/tasks/affinity-setup.md","Set Up Affinity for Deal Pipelines") | D7: =HYPERLINK('Link Config'!$B$2&"plugins/vc/skills/vc-affinity-discovery/SKILL.md","VC Affinity Discovery")
A8: Deal Pipeline | B8: Setup | C8: =HYPERLINK('Link Config'!$B$2&"plugins/vc/tasks/affinity-setup.md","Set Up Affinity for Deal Pipelines") | D8: =HYPERLINK('Link Config'!$B$2&"plugins/vc/skills/vc-affinity-sync-read/SKILL.md","VC Affinity Sync Read")
A9: Deal Pipeline | B9: Setup | C9: =HYPERLINK('Link Config'!$B$2&"plugins/vc/tasks/affinity-setup.md","Set Up Affinity for Deal Pipelines") | D9: =HYPERLINK('Link Config'!$B$2&"plugins/vc/skills/vc-affinity-sync-write/SKILL.md","VC Affinity Sync Write")
A10: Deal Pipeline | B10: Setup | C10: =HYPERLINK('Link Config'!$B$2&"plugins/vc/tasks/affinity-setup.md","Set Up Affinity for Deal Pipelines") | D10: =HYPERLINK('Link Config'!$B$2&"plugins/vc/skills/citation-enforcement/SKILL.md","Citation Enforcement")
A11: Deal Pipeline | B11: Setup | C11: =HYPERLINK('Link Config'!$B$2&"plugins/vc/tasks/affinity-deal-room-import.md","Import Affinity Deal Pipeline Seed") | D11: =HYPERLINK('Link Config'!$B$2&"plugins/vc/skills/vc-affinity-deal-room-import/SKILL.md","VC Affinity Deal Pipeline Import")
A12: Deal Pipeline | B12: Setup | C12: =HYPERLINK('Link Config'!$B$2&"plugins/vc/tasks/affinity-deal-room-import.md","Import Affinity Deal Pipeline Seed") | D12: =HYPERLINK('Link Config'!$B$2&"plugins/vc/skills/vc-affinity-sync-read/SKILL.md","VC Affinity Sync Read")
A13: Deal Pipeline | B13: Setup | C13: =HYPERLINK('Link Config'!$B$2&"plugins/vc/tasks/affinity-deal-room-import.md","Import Affinity Deal Pipeline Seed") | D13: =HYPERLINK('Link Config'!$B$2&"plugins/vc/skills/deal-room-setup-and-source-ingestion/SKILL.md","Deal Pipeline Setup & Source Ingestion")
A14: Deal Pipeline | B14: Setup | C14: =HYPERLINK('Link Config'!$B$2&"plugins/vc/tasks/affinity-deal-room-import.md","Import Affinity Deal Pipeline Seed") | D14: =HYPERLINK('Link Config'!$B$2&"plugins/vc/skills/citation-enforcement/SKILL.md","Citation Enforcement")
A15: Deal Pipeline | B15: General | C15: =HYPERLINK('Link Config'!$B$2&"plugins/vc/tasks/prepare-initial-call.md","Prepare Meeting") | D15: =HYPERLINK('Link Config'!$B$2&"plugins/vc/skills/meeting-prep-and-summary/SKILL.md","Meeting Prep & Summary")
A16: Deal Pipeline | B16: General | C16: =HYPERLINK('Link Config'!$B$2&"plugins/vc/tasks/prepare-initial-call.md","Prepare Meeting") | D16: =HYPERLINK('Link Config'!$B$2&"plugins/vc/skills/company-research-and-enrichment/SKILL.md","Company Research & Enrichment")
A17: Deal Pipeline | B17: General | C17: =HYPERLINK('Link Config'!$B$2&"plugins/vc/tasks/prepare-initial-call.md","Prepare Meeting") | D17: =HYPERLINK('Link Config'!$B$2&"plugins/vc/skills/citation-enforcement/SKILL.md","Citation Enforcement")
A18: Deal Pipeline | B18: General | C18: =HYPERLINK('Link Config'!$B$2&"plugins/vc/tasks/prepare-initial-call.md","Prepare Meeting") | D18: =HYPERLINK('Link Config'!$B$2&"plugins/vc/skills/pitch-deck-explainer/SKILL.md","Pitch Deck Explainer")
A19: Deal Pipeline | B19: General | C19: =HYPERLINK('Link Config'!$B$2&"plugins/vc/tasks/request-founder-materials.md","Request Founder Materials") | D19: =HYPERLINK('Link Config'!$B$2&"plugins/vc/skills/citation-enforcement/SKILL.md","Citation Enforcement")
A20: Deal Pipeline | B20: General | C20: =HYPERLINK('Link Config'!$B$2&"plugins/vc/tasks/request-founder-materials.md","Request Founder Materials") | D20: =HYPERLINK('Link Config'!$B$2&"plugins/vc/skills/founder-materials-request/SKILL.md","Founder Materials Request")
A21: Deal Pipeline | B21: General | C21: =HYPERLINK('Link Config'!$B$2&"plugins/vc/tasks/summarize-initial-call.md","Summarize Meeting Records") | D21: =HYPERLINK('Link Config'!$B$2&"plugins/vc/skills/meeting-prep-and-summary/SKILL.md","Meeting Prep & Summary")
A22: Deal Pipeline | B22: General | C22: =HYPERLINK('Link Config'!$B$2&"plugins/vc/tasks/summarize-initial-call.md","Summarize Meeting Records") | D22: =HYPERLINK('Link Config'!$B$2&"plugins/vc/skills/citation-enforcement/SKILL.md","Citation Enforcement")
A23: Deal Pipeline | B23: General | C23: =HYPERLINK('Link Config'!$B$2&"plugins/vc/tasks/summarize-initial-call.md","Summarize Meeting Records") | D23: =HYPERLINK('Link Config'!$B$2&"plugins/vc/skills/vc-task-and-next-step-generation/SKILL.md","VC Task & Next-Step Generation")
A24: Deal Pipeline | B24: General | C24: =HYPERLINK('Link Config'!$B$2&"plugins/vc/tasks/review-opportunity-status.md","Review Opportunity Status") | D24: =HYPERLINK('Link Config'!$B$2&"plugins/vc/skills/citation-enforcement/SKILL.md","Citation Enforcement")
A25: Deal Pipeline | B25: General | C25: =HYPERLINK('Link Config'!$B$2&"plugins/vc/tasks/review-opportunity-status.md","Review Opportunity Status") | D25: =HYPERLINK('Link Config'!$B$2&"plugins/vc/skills/vc-task-and-next-step-generation/SKILL.md","VC Task & Next-Step Generation")
A26: Deal Pipeline | B26: Integration Support | C26: =HYPERLINK('Link Config'!$B$2&"plugins/vc/tasks/affinity-sync-read.md","Preview Affinity Pipeline Import") | D26: =HYPERLINK('Link Config'!$B$2&"plugins/vc/skills/vc-affinity-sync-read/SKILL.md","VC Affinity Sync Read")
A27: Deal Pipeline | B27: Integration Support | C27: =HYPERLINK('Link Config'!$B$2&"plugins/vc/tasks/affinity-sync-read.md","Preview Affinity Pipeline Import") | D27: =HYPERLINK('Link Config'!$B$2&"plugins/vc/skills/citation-enforcement/SKILL.md","Citation Enforcement")
A28: Deal Pipeline | B28: Integration Support | C28: =HYPERLINK('Link Config'!$B$2&"plugins/vc/tasks/affinity-sync-write.md","Draft Affinity Write-Back Proposals") | D28: =HYPERLINK('Link Config'!$B$2&"plugins/vc/skills/vc-affinity-sync-write/SKILL.md","VC Affinity Sync Write")
A29: Deal Pipeline | B29: Integration Support | C29: =HYPERLINK('Link Config'!$B$2&"plugins/vc/tasks/affinity-sync-write.md","Draft Affinity Write-Back Proposals") | D29: =HYPERLINK('Link Config'!$B$2&"plugins/vc/skills/citation-enforcement/SKILL.md","Citation Enforcement")
A30: Deal Pipeline | B30: Integration Support | C30: =HYPERLINK('Link Config'!$B$2&"plugins/vc/tasks/google-drive-sync-write.md","Draft Google Drive File Proposals") | D30: =HYPERLINK('Link Config'!$B$2&"plugins/vc/skills/vc-google-drive-sync-write/SKILL.md","VC Google Drive Sync Write")
A31: Deal Pipeline | B31: Integration Support | C31: =HYPERLINK('Link Config'!$B$2&"plugins/vc/tasks/google-drive-sync-write.md","Draft Google Drive File Proposals") | D31: =HYPERLINK('Link Config'!$B$2&"plugins/vc/skills/citation-enforcement/SKILL.md","Citation Enforcement")
A32: Deal Pipeline | B32: Integration Support | C32: =HYPERLINK('Link Config'!$B$2&"plugins/vc/tasks/notion-sync-write.md","Draft Notion Update Proposals") | D32: =HYPERLINK('Link Config'!$B$2&"plugins/vc/skills/vc-notion-sync-write/SKILL.md","VC Notion Sync Write")
A33: Deal Pipeline | B33: Integration Support | C33: =HYPERLINK('Link Config'!$B$2&"plugins/vc/tasks/notion-sync-write.md","Draft Notion Update Proposals") | D33: =HYPERLINK('Link Config'!$B$2&"plugins/vc/skills/citation-enforcement/SKILL.md","Citation Enforcement")
A34: Deal Pipeline | B34: Integration Support | C34: =HYPERLINK('Link Config'!$B$2&"plugins/vc/tasks/slack-sync-write.md","Draft Slack Handoff Notifications") | D34: =HYPERLINK('Link Config'!$B$2&"plugins/vc/skills/vc-slack-sync-write/SKILL.md","VC Slack Sync Write")
A35: Deal Pipeline | B35: Integration Support | C35: =HYPERLINK('Link Config'!$B$2&"plugins/vc/tasks/slack-sync-write.md","Draft Slack Handoff Notifications") | D35: =HYPERLINK('Link Config'!$B$2&"plugins/vc/skills/citation-enforcement/SKILL.md","Citation Enforcement")
A36: Deal Pipeline | B36: Integration Support | C36: =HYPERLINK('Link Config'!$B$2&"plugins/vc/tasks/affinity-discovery.md","Explore Affinity Lists and Stages") | D36: =HYPERLINK('Link Config'!$B$2&"plugins/vc/skills/vc-affinity-discovery/SKILL.md","VC Affinity Discovery")
A37: Deal Pipeline | B37: Integration Support | C37: =HYPERLINK('Link Config'!$B$2&"plugins/vc/tasks/affinity-discovery.md","Explore Affinity Lists and Stages") | D37: =HYPERLINK('Link Config'!$B$2&"plugins/vc/skills/citation-enforcement/SKILL.md","Citation Enforcement")
A38: Deal Pipeline | B38: Integration Support | C38: =HYPERLINK('Link Config'!$B$2&"plugins/vc/tasks/google-drive-discovery.md","Explore Google Drive Sources") | D38: =HYPERLINK('Link Config'!$B$2&"plugins/vc/skills/vc-google-drive-discovery/SKILL.md","VC Google Drive Discovery")
A39: Deal Pipeline | B39: Integration Support | C39: =HYPERLINK('Link Config'!$B$2&"plugins/vc/tasks/google-drive-discovery.md","Explore Google Drive Sources") | D39: =HYPERLINK('Link Config'!$B$2&"plugins/vc/skills/citation-enforcement/SKILL.md","Citation Enforcement")
A40: Deal Pipeline | B40: Integration Support | C40: =HYPERLINK('Link Config'!$B$2&"plugins/vc/tasks/harmonic-discovery.md","Explore Harmonic Source Scopes") | D40: =HYPERLINK('Link Config'!$B$2&"plugins/vc/skills/vc-harmonic-discovery/SKILL.md","VC Harmonic Discovery")
A41: Deal Pipeline | B41: Integration Support | C41: =HYPERLINK('Link Config'!$B$2&"plugins/vc/tasks/harmonic-discovery.md","Explore Harmonic Source Scopes") | D41: =HYPERLINK('Link Config'!$B$2&"plugins/vc/skills/citation-enforcement/SKILL.md","Citation Enforcement")
A42: Deal Pipeline | B42: Integration Support | C42: =HYPERLINK('Link Config'!$B$2&"plugins/vc/tasks/notion-discovery.md","Explore Notion Pages and Databases") | D42: =HYPERLINK('Link Config'!$B$2&"plugins/vc/skills/vc-notion-discovery/SKILL.md","VC Notion Discovery")
A43: Deal Pipeline | B43: Integration Support | C43: =HYPERLINK('Link Config'!$B$2&"plugins/vc/tasks/notion-discovery.md","Explore Notion Pages and Databases") | D43: =HYPERLINK('Link Config'!$B$2&"plugins/vc/skills/citation-enforcement/SKILL.md","Citation Enforcement")
A44: Deal Pipeline | B44: Integration Support | C44: =HYPERLINK('Link Config'!$B$2&"plugins/vc/tasks/slack-discovery.md","Explore Slack Channels for VC Context") | D44: =HYPERLINK('Link Config'!$B$2&"plugins/vc/skills/vc-slack-discovery/SKILL.md","VC Slack Discovery")
A45: Deal Pipeline | B45: Integration Support | C45: =HYPERLINK('Link Config'!$B$2&"plugins/vc/tasks/slack-discovery.md","Explore Slack Channels for VC Context") | D45: =HYPERLINK('Link Config'!$B$2&"plugins/vc/skills/citation-enforcement/SKILL.md","Citation Enforcement")
A46: Deal Pipeline | B46: Pipeline Management | C46: =HYPERLINK('Link Config'!$B$2&"plugins/vc/tasks/prepare-deal-flow-agenda.md","Prepare Deal Flow Agenda") | D46: =HYPERLINK('Link Config'!$B$2&"plugins/vc/skills/citation-enforcement/SKILL.md","Citation Enforcement")
A47: Deal Pipeline | B47: Pipeline Management | C47: =HYPERLINK('Link Config'!$B$2&"plugins/vc/tasks/prepare-deal-flow-agenda.md","Prepare Deal Flow Agenda") | D47: =HYPERLINK('Link Config'!$B$2&"plugins/vc/skills/vc-task-and-next-step-generation/SKILL.md","VC Task & Next-Step Generation")
A48: Deal Pipeline | B48: Integration Support | C48: =HYPERLINK('Link Config'!$B$2&"plugins/vc/tasks/google-drive-sync-read.md","Preview Google Drive Context") | D48: =HYPERLINK('Link Config'!$B$2&"plugins/vc/skills/vc-google-drive-sync-read/SKILL.md","VC Google Drive Sync Read")
A49: Deal Pipeline | B49: Integration Support | C49: =HYPERLINK('Link Config'!$B$2&"plugins/vc/tasks/google-drive-sync-read.md","Preview Google Drive Context") | D49: =HYPERLINK('Link Config'!$B$2&"plugins/vc/skills/citation-enforcement/SKILL.md","Citation Enforcement")
A50: Deal Pipeline | B50: Integration Support | C50: =HYPERLINK('Link Config'!$B$2&"plugins/vc/tasks/harmonic-sync-read.md","Preview Harmonic Search Results") | D50: =HYPERLINK('Link Config'!$B$2&"plugins/vc/skills/vc-harmonic-sync-read/SKILL.md","VC Harmonic Sync Read")
A51: Deal Pipeline | B51: Integration Support | C51: =HYPERLINK('Link Config'!$B$2&"plugins/vc/tasks/harmonic-sync-read.md","Preview Harmonic Search Results") | D51: =HYPERLINK('Link Config'!$B$2&"plugins/vc/skills/citation-enforcement/SKILL.md","Citation Enforcement")
A52: Deal Pipeline | B52: Integration Support | C52: =HYPERLINK('Link Config'!$B$2&"plugins/vc/tasks/notion-sync-read.md","Preview Notion Context") | D52: =HYPERLINK('Link Config'!$B$2&"plugins/vc/skills/vc-notion-sync-read/SKILL.md","VC Notion Sync Read")
A53: Deal Pipeline | B53: Integration Support | C53: =HYPERLINK('Link Config'!$B$2&"plugins/vc/tasks/notion-sync-read.md","Preview Notion Context") | D53: =HYPERLINK('Link Config'!$B$2&"plugins/vc/skills/citation-enforcement/SKILL.md","Citation Enforcement")
A54: Deal Pipeline | B54: Integration Support | C54: =HYPERLINK('Link Config'!$B$2&"plugins/vc/tasks/slack-sync-read.md","Preview Slack Deal Context") | D54: =HYPERLINK('Link Config'!$B$2&"plugins/vc/skills/vc-slack-sync-read/SKILL.md","VC Slack Sync Read")
A55: Deal Pipeline | B55: Integration Support | C55: =HYPERLINK('Link Config'!$B$2&"plugins/vc/tasks/slack-sync-read.md","Preview Slack Deal Context") | D55: =HYPERLINK('Link Config'!$B$2&"plugins/vc/skills/citation-enforcement/SKILL.md","Citation Enforcement")
A56: Deal Pipeline | B56: Integration Support | C56: =HYPERLINK('Link Config'!$B$2&"plugins/vc/tasks/google-drive-setup.md","Set Up Google Drive for Deal Pipelines") | D56: =HYPERLINK('Link Config'!$B$2&"plugins/vc/skills/vc-google-drive-discovery/SKILL.md","VC Google Drive Discovery")
A57: Deal Pipeline | B57: Integration Support | C57: =HYPERLINK('Link Config'!$B$2&"plugins/vc/tasks/google-drive-setup.md","Set Up Google Drive for Deal Pipelines") | D57: =HYPERLINK('Link Config'!$B$2&"plugins/vc/skills/vc-google-drive-sync-read/SKILL.md","VC Google Drive Sync Read")
A58: Deal Pipeline | B58: Integration Support | C58: =HYPERLINK('Link Config'!$B$2&"plugins/vc/tasks/google-drive-setup.md","Set Up Google Drive for Deal Pipelines") | D58: =HYPERLINK('Link Config'!$B$2&"plugins/vc/skills/vc-google-drive-sync-write/SKILL.md","VC Google Drive Sync Write")
A59: Deal Pipeline | B59: Integration Support | C59: =HYPERLINK('Link Config'!$B$2&"plugins/vc/tasks/google-drive-setup.md","Set Up Google Drive for Deal Pipelines") | D59: =HYPERLINK('Link Config'!$B$2&"plugins/vc/skills/citation-enforcement/SKILL.md","Citation Enforcement")
A60: Deal Pipeline | B60: Integration Support | C60: =HYPERLINK('Link Config'!$B$2&"plugins/vc/tasks/harmonic-setup.md","Set Up Harmonic for Deal Pipelines") | D60: =HYPERLINK('Link Config'!$B$2&"plugins/vc/skills/vc-harmonic-discovery/SKILL.md","VC Harmonic Discovery")
A61: Deal Pipeline | B61: Integration Support | C61: =HYPERLINK('Link Config'!$B$2&"plugins/vc/tasks/harmonic-setup.md","Set Up Harmonic for Deal Pipelines") | D61: =HYPERLINK('Link Config'!$B$2&"plugins/vc/skills/vc-harmonic-sync-read/SKILL.md","VC Harmonic Sync Read")
A62: Deal Pipeline | B62: Integration Support | C62: =HYPERLINK('Link Config'!$B$2&"plugins/vc/tasks/harmonic-setup.md","Set Up Harmonic for Deal Pipelines") | D62: =HYPERLINK('Link Config'!$B$2&"plugins/vc/skills/citation-enforcement/SKILL.md","Citation Enforcement")
A63: Deal Pipeline | B63: Integration Support | C63: =HYPERLINK('Link Config'!$B$2&"plugins/vc/tasks/notion-setup.md","Set Up Notion for Deal Pipelines") | D63: =HYPERLINK('Link Config'!$B$2&"plugins/vc/skills/vc-notion-discovery/SKILL.md","VC Notion Discovery")
A64: Deal Pipeline | B64: Integration Support | C64: =HYPERLINK('Link Config'!$B$2&"plugins/vc/tasks/notion-setup.md","Set Up Notion for Deal Pipelines") | D64: =HYPERLINK('Link Config'!$B$2&"plugins/vc/skills/vc-notion-sync-read/SKILL.md","VC Notion Sync Read")
A65: Deal Pipeline | B65: Integration Support | C65: =HYPERLINK('Link Config'!$B$2&"plugins/vc/tasks/notion-setup.md","Set Up Notion for Deal Pipelines") | D65: =HYPERLINK('Link Config'!$B$2&"plugins/vc/skills/vc-notion-sync-write/SKILL.md","VC Notion Sync Write")
A66: Deal Pipeline | B66: Integration Support | C66: =HYPERLINK('Link Config'!$B$2&"plugins/vc/tasks/notion-setup.md","Set Up Notion for Deal Pipelines") | D66: =HYPERLINK('Link Config'!$B$2&"plugins/vc/skills/citation-enforcement/SKILL.md","Citation Enforcement")
A67: Deal Pipeline | B67: Integration Support | C67: =HYPERLINK('Link Config'!$B$2&"plugins/vc/tasks/slack-setup.md","Set Up Slack for Deal Pipelines") | D67: =HYPERLINK('Link Config'!$B$2&"plugins/vc/skills/vc-slack-discovery/SKILL.md","VC Slack Discovery")
A68: Deal Pipeline | B68: Integration Support | C68: =HYPERLINK('Link Config'!$B$2&"plugins/vc/tasks/slack-setup.md","Set Up Slack for Deal Pipelines") | D68: =HYPERLINK('Link Config'!$B$2&"plugins/vc/skills/vc-slack-sync-read/SKILL.md","VC Slack Sync Read")
A69: Deal Pipeline | B69: Integration Support | C69: =HYPERLINK('Link Config'!$B$2&"plugins/vc/tasks/slack-setup.md","Set Up Slack for Deal Pipelines") | D69: =HYPERLINK('Link Config'!$B$2&"plugins/vc/skills/vc-slack-sync-write/SKILL.md","VC Slack Sync Write")
A70: Deal Pipeline | B70: Integration Support | C70: =HYPERLINK('Link Config'!$B$2&"plugins/vc/tasks/slack-setup.md","Set Up Slack for Deal Pipelines") | D70: =HYPERLINK('Link Config'!$B$2&"plugins/vc/skills/citation-enforcement/SKILL.md","Citation Enforcement")
A71: Deal Pipeline | B71: Screening | C71: =HYPERLINK('Link Config'!$B$2&"plugins/vc/tasks/run-investment-screen.md","Run Investment Fit Screen") | D71: =HYPERLINK('Link Config'!$B$2&"plugins/vc/skills/investment-screening-framework/SKILL.md","Investment Screening Framework")
A72: Deal Pipeline | B72: Screening | C72: =HYPERLINK('Link Config'!$B$2&"plugins/vc/tasks/run-investment-screen.md","Run Investment Fit Screen") | D72: =HYPERLINK('Link Config'!$B$2&"plugins/vc/skills/red-flags-scanner/SKILL.md","Red Flags Scanner")
A73: Deal Pipeline | B73: Screening | C73: =HYPERLINK('Link Config'!$B$2&"plugins/vc/tasks/run-investment-screen.md","Run Investment Fit Screen") | D73: =HYPERLINK('Link Config'!$B$2&"plugins/vc/skills/citation-enforcement/SKILL.md","Citation Enforcement")
A74: Deal Pipeline | B74: Evaluation | C74: =HYPERLINK('Link Config'!$B$2&"plugins/vc/tasks/run-follow-up-evaluation.md","Run Opportunity Evaluation") | D74: =HYPERLINK('Link Config'!$B$2&"plugins/vc/skills/investment-diligence-question-framework/SKILL.md","Investment Diligence Question Framework")
A75: Deal Pipeline | B75: Evaluation | C75: =HYPERLINK('Link Config'!$B$2&"plugins/vc/tasks/run-follow-up-evaluation.md","Run Opportunity Evaluation") | D75: =HYPERLINK('Link Config'!$B$2&"plugins/vc/skills/red-flags-scanner/SKILL.md","Red Flags Scanner")
A76: Deal Pipeline | B76: Evaluation | C76: =HYPERLINK('Link Config'!$B$2&"plugins/vc/tasks/run-follow-up-evaluation.md","Run Opportunity Evaluation") | D76: =HYPERLINK('Link Config'!$B$2&"plugins/vc/skills/citation-enforcement/SKILL.md","Citation Enforcement")
A77: Deal Pipeline | B77: Evaluation | C77: =HYPERLINK('Link Config'!$B$2&"plugins/vc/tasks/run-commercial-evaluation.md","Run Commercial Evaluation") | D77: =HYPERLINK('Link Config'!$B$2&"plugins/vc/skills/commercial-evaluation-and-market-risk/SKILL.md","Commercial Evaluation & Market Risk")
A78: Deal Pipeline | B78: Evaluation | C78: =HYPERLINK('Link Config'!$B$2&"plugins/vc/tasks/run-commercial-evaluation.md","Run Commercial Evaluation") | D78: =HYPERLINK('Link Config'!$B$2&"plugins/vc/skills/citation-enforcement/SKILL.md","Citation Enforcement")
A79: Deal Pipeline | B79: Evaluation | C79: =HYPERLINK('Link Config'!$B$2&"plugins/vc/tasks/run-technical-evaluation.md","Run Technical Evaluation") | D79: =HYPERLINK('Link Config'!$B$2&"plugins/vc/skills/technical-evaluation-and-product-risk/SKILL.md","Technical Evaluation & Product Risk")
A80: Deal Pipeline | B80: Evaluation | C80: =HYPERLINK('Link Config'!$B$2&"plugins/vc/tasks/run-technical-evaluation.md","Run Technical Evaluation") | D80: =HYPERLINK('Link Config'!$B$2&"plugins/vc/skills/red-flags-scanner/SKILL.md","Red Flags Scanner")
A81: Deal Pipeline | B81: Evaluation | C81: =HYPERLINK('Link Config'!$B$2&"plugins/vc/tasks/run-technical-evaluation.md","Run Technical Evaluation") | D81: =HYPERLINK('Link Config'!$B$2&"plugins/vc/skills/citation-enforcement/SKILL.md","Citation Enforcement")
A82: Deal Pipeline | B82: Evaluation | C82: =HYPERLINK('Link Config'!$B$2&"plugins/vc/tasks/run-financial-evaluation.md","Run Financial Evaluation") | D82: =HYPERLINK('Link Config'!$B$2&"plugins/vc/skills/financial-evaluation-and-financing-risk/SKILL.md","Financial Evaluation & Financing Risk")
A83: Deal Pipeline | B83: Evaluation | C83: =HYPERLINK('Link Config'!$B$2&"plugins/vc/tasks/run-financial-evaluation.md","Run Financial Evaluation") | D83: =HYPERLINK('Link Config'!$B$2&"plugins/vc/skills/citation-enforcement/SKILL.md","Citation Enforcement")
A84: Deal Pipeline | B84: Evaluation | C84: =HYPERLINK('Link Config'!$B$2&"plugins/vc/tasks/run-team-evaluation.md","Run Team Evaluation") | D84: =HYPERLINK('Link Config'!$B$2&"plugins/vc/skills/team-evaluation-and-founder-risk/SKILL.md","Team Evaluation & Founder Risk")
A85: Deal Pipeline | B85: Evaluation | C85: =HYPERLINK('Link Config'!$B$2&"plugins/vc/tasks/run-team-evaluation.md","Run Team Evaluation") | D85: =HYPERLINK('Link Config'!$B$2&"plugins/vc/skills/red-flags-scanner/SKILL.md","Red Flags Scanner")
A86: Deal Pipeline | B86: Evaluation | C86: =HYPERLINK('Link Config'!$B$2&"plugins/vc/tasks/run-team-evaluation.md","Run Team Evaluation") | D86: =HYPERLINK('Link Config'!$B$2&"plugins/vc/skills/citation-enforcement/SKILL.md","Citation Enforcement")
A87: Deal Pipeline | B87: Evaluation | C87: =HYPERLINK('Link Config'!$B$2&"plugins/vc/tasks/generate-diligence-questions.md","Generate Diligence Questions") | D87: =HYPERLINK('Link Config'!$B$2&"plugins/vc/skills/investment-diligence-question-framework/SKILL.md","Investment Diligence Question Framework")
A88: Deal Pipeline | B88: Evaluation | C88: =HYPERLINK('Link Config'!$B$2&"plugins/vc/tasks/generate-diligence-questions.md","Generate Diligence Questions") | D88: =HYPERLINK('Link Config'!$B$2&"plugins/vc/skills/citation-enforcement/SKILL.md","Citation Enforcement")
A89: Deal Pipeline | B89: Decision Review | C89: =HYPERLINK('Link Config'!$B$2&"plugins/vc/tasks/prepare-team-review-pack.md","Prepare Team Review Pack") | D89: =HYPERLINK('Link Config'!$B$2&"plugins/vc/skills/ic-memo-assembly/SKILL.md","IC Memo Assembly")
A90: Deal Pipeline | B90: Decision Review | C90: =HYPERLINK('Link Config'!$B$2&"plugins/vc/tasks/prepare-team-review-pack.md","Prepare Team Review Pack") | D90: =HYPERLINK('Link Config'!$B$2&"plugins/vc/skills/citation-enforcement/SKILL.md","Citation Enforcement")
A91: Deal Pipeline | B91: Decision Review | C91: =HYPERLINK('Link Config'!$B$2&"plugins/vc/tasks/prepare-partner-review-pack.md","Prepare Partner Review Pack") | D91: =HYPERLINK('Link Config'!$B$2&"plugins/vc/skills/ic-memo-assembly/SKILL.md","IC Memo Assembly")
A92: Deal Pipeline | B92: Decision Review | C92: =HYPERLINK('Link Config'!$B$2&"plugins/vc/tasks/prepare-partner-review-pack.md","Prepare Partner Review Pack") | D92: =HYPERLINK('Link Config'!$B$2&"plugins/vc/skills/citation-enforcement/SKILL.md","Citation Enforcement")
A93: Deal Pipeline | B93: Decision Review | C93: =HYPERLINK('Link Config'!$B$2&"plugins/vc/tasks/create-ic-memo.md","Create IC Memo") | D93: =HYPERLINK('Link Config'!$B$2&"plugins/vc/skills/ic-memo-assembly/SKILL.md","IC Memo Assembly")
A94: Deal Pipeline | B94: Decision Review | C94: =HYPERLINK('Link Config'!$B$2&"plugins/vc/tasks/create-ic-memo.md","Create IC Memo") | D94: =HYPERLINK('Link Config'!$B$2&"plugins/vc/skills/citation-enforcement/SKILL.md","Citation Enforcement")
A95: Deal Pipeline | B95: Decision Review | C95: =HYPERLINK('Link Config'!$B$2&"plugins/vc/tasks/create-ic-memo.md","Create IC Memo") | D95: =HYPERLINK('Link Config'!$B$2&"plugins/vc/skills/ic-risk-checklist-and-decision-log/SKILL.md","IC Risk Checklist & Decision Log")
A96: Deal Pipeline | B96: Decision Review | C96: =HYPERLINK('Link Config'!$B$2&"plugins/vc/tasks/prepare-ic-agenda.md","Prepare IC Agenda") | D96: =HYPERLINK('Link Config'!$B$2&"plugins/vc/skills/meeting-prep-and-summary/SKILL.md","Meeting Prep & Summary")
A97: Deal Pipeline | B97: Decision Review | C97: =HYPERLINK('Link Config'!$B$2&"plugins/vc/tasks/prepare-ic-agenda.md","Prepare IC Agenda") | D97: =HYPERLINK('Link Config'!$B$2&"plugins/vc/skills/citation-enforcement/SKILL.md","Citation Enforcement")
A98: Deal Pipeline | B98: Decision Review | C98: =HYPERLINK('Link Config'!$B$2&"plugins/vc/tasks/prepare-ic-agenda.md","Prepare IC Agenda") | D98: =HYPERLINK('Link Config'!$B$2&"plugins/vc/skills/ic-risk-checklist-and-decision-log/SKILL.md","IC Risk Checklist & Decision Log")
A99: Deal Pipeline | B99: Decision Review | C99: =HYPERLINK('Link Config'!$B$2&"plugins/vc/tasks/review-ic-memo.md","Review IC Memo") | D99: =HYPERLINK('Link Config'!$B$2&"plugins/vc/skills/citation-enforcement/SKILL.md","Citation Enforcement")
A100: Deal Pipeline | B100: Decision Review | C100: =HYPERLINK('Link Config'!$B$2&"plugins/vc/tasks/review-ic-memo.md","Review IC Memo") | D100: =HYPERLINK('Link Config'!$B$2&"plugins/vc/skills/ic-memo-assembly/SKILL.md","IC Memo Assembly")
...

Sheet Task Document Links
A1: Project | B1: Stage | C1: Task | D1: Document | E1: Usage | F1: Output Field
A2: Project Type | B2: Stage / Pseudo-stage | C2: Linked task | D2: Linked document | E2: Document usage | F2: Output field
A3: Deal Pipeline | B3: Setup | C3: =HYPERLINK('Link Config'!$B$2&"plugins/vc/tasks/screen-inbound-opportunity.md","Capture Opportunity Intake") | D3: =HYPERLINK('Link Config'!$B$2&"plugins/vc/alludium/documents/deal-room/deal-room-sop.md","Deal Pipeline Operating SOP (vc.document.deal_room_sop)") | E3: operating_guidance
A4: Deal Pipeline | B4: Setup | C4: =HYPERLINK('Link Config'!$B$2&"plugins/vc/tasks/screen-inbound-opportunity.md","Capture Opportunity Intake") | D4: =HYPERLINK('Link Config'!$B$2&"plugins/vc/alludium/documents/shared/evidence-citation-style-guide.md","Evidence And Citation Style Guide (vc.document.evidence_citation_style_guide)") | E4: style_guide
A5: Deal Pipeline | B5: Setup | C5: =HYPERLINK('Link Config'!$B$2&"plugins/vc/tasks/screen-inbound-opportunity.md","Capture Opportunity Intake") | D5: =HYPERLINK('Link Config'!$B$2&"plugins/vc/alludium/documents/shared/template-use-guidance.md","Template Use Guidance (vc.document.template_use_guidance)") | E5: operating_guidance
A6: Deal Pipeline | B6: General | C6: =HYPERLINK('Link Config'!$B$2&"plugins/vc/tasks/prepare-initial-call.md","Prepare Meeting") | D6: =HYPERLINK('Link Config'!$B$2&"plugins/vc/alludium/documents/deal-room/initial-call-brief-template.md","Initial Call Brief Template (vc.document.initial_call_brief_template)") | E6: output_template | F6: initial_call_brief_artifact_id
A7: Deal Pipeline | B7: General | C7: =HYPERLINK('Link Config'!$B$2&"plugins/vc/tasks/prepare-initial-call.md","Prepare Meeting") | D7: =HYPERLINK('Link Config'!$B$2&"plugins/vc/alludium/documents/shared/evidence-citation-style-guide.md","Evidence And Citation Style Guide (vc.document.evidence_citation_style_guide)") | E7: style_guide
A8: Deal Pipeline | B8: General | C8: =HYPERLINK('Link Config'!$B$2&"plugins/vc/tasks/prepare-initial-call.md","Prepare Meeting") | D8: =HYPERLINK('Link Config'!$B$2&"plugins/vc/alludium/documents/shared/template-use-guidance.md","Template Use Guidance (vc.document.template_use_guidance)") | E8: operating_guidance
A9: Deal Pipeline | B9: General | C9: =HYPERLINK('Link Config'!$B$2&"plugins/vc/tasks/request-founder-materials.md","Request Founder Materials") | D9: =HYPERLINK('Link Config'!$B$2&"plugins/vc/alludium/documents/deal-room/founder-materials-request-template.md","Founder Materials Request Template (vc.document.founder_materials_request_template)") | E9: output_template | F9: founder_materials_request_artifact_id
A10: Deal Pipeline | B10: General | C10: =HYPERLINK('Link Config'!$B$2&"plugins/vc/tasks/request-founder-materials.md","Request Founder Materials") | D10: =HYPERLINK('Link Config'!$B$2&"plugins/vc/alludium/documents/shared/file-naming-source-index-sop.md","File Naming And Source Index SOP (vc.document.file_naming_source_index_sop)") | E10: operating_guidance
A11: Deal Pipeline | B11: General | C11: =HYPERLINK('Link Config'!$B$2&"plugins/vc/tasks/request-founder-materials.md","Request Founder Materials") | D11: =HYPERLINK('Link Config'!$B$2&"plugins/vc/alludium/documents/shared/template-use-guidance.md","Template Use Guidance (vc.document.template_use_guidance)") | E11: operating_guidance
A12: Deal Pipeline | B12: General | C12: =HYPERLINK('Link Config'!$B$2&"plugins/vc/tasks/summarize-initial-call.md","Summarize Meeting Records") | D12: =HYPERLINK('Link Config'!$B$2&"plugins/vc/alludium/documents/deal-room/customer-insights-summary-template.md","Customer Insights Summary Template (vc.document.customer_insights_summary_template)") | E12: output_template | F12: customer_insights_artifact_id
A13: Deal Pipeline | B13: General | C13: =HYPERLINK('Link Config'!$B$2&"plugins/vc/tasks/summarize-initial-call.md","Summarize Meeting Records") | D13: =HYPERLINK('Link Config'!$B$2&"plugins/vc/alludium/documents/shared/evidence-citation-style-guide.md","Evidence And Citation Style Guide (vc.document.evidence_citation_style_guide)") | E13: style_guide
A14: Deal Pipeline | B14: General | C14: =HYPERLINK('Link Config'!$B$2&"plugins/vc/tasks/summarize-initial-call.md","Summarize Meeting Records") | D14: =HYPERLINK('Link Config'!$B$2&"plugins/vc/alludium/documents/shared/template-use-guidance.md","Template Use Guidance (vc.document.template_use_guidance)") | E14: operating_guidance
A15: Deal Pipeline | B15: General | C15: =HYPERLINK('Link Config'!$B$2&"plugins/vc/tasks/review-opportunity-status.md","Review Opportunity Status") | D15: =HYPERLINK('Link Config'!$B$2&"plugins/vc/alludium/documents/deal-room/deal-room-sop.md","Deal Pipeline Operating SOP (vc.document.deal_room_sop)") | E15: operating_guidance
A16: Deal Pipeline | B16: General | C16: =HYPERLINK('Link Config'!$B$2&"plugins/vc/tasks/review-opportunity-status.md","Review Opportunity Status") | D16: =HYPERLINK('Link Config'!$B$2&"plugins/vc/alludium/documents/shared/opportunity-evaluation-framework.md","Opportunity Evaluation Framework (vc.document.opportunity_evaluation_framework)") | E16: methodology
A17: Deal Pipeline | B17: General | C17: =HYPERLINK('Link Config'!$B$2&"plugins/vc/tasks/review-opportunity-status.md","Review Opportunity Status") | D17: =HYPERLINK('Link Config'!$B$2&"plugins/vc/alludium/documents/shared/evaluation-workstream-guide.md","Evaluation Workstream Guide (vc.document.evaluation_workstream_guide)") | E17: methodology
A18: Deal Pipeline | B18: General | C18: =HYPERLINK('Link Config'!$B$2&"plugins/vc/tasks/review-opportunity-status.md","Review Opportunity Status") | D18: =HYPERLINK('Link Config'!$B$2&"plugins/vc/alludium/documents/shared/evidence-citation-style-guide.md","Evidence And Citation Style Guide (vc.document.evidence_citation_style_guide)") | E18: style_guide
A19: Deal Pipeline | B19: General | C19: =HYPERLINK('Link Config'!$B$2&"plugins/vc/tasks/review-opportunity-status.md","Review Opportunity Status") | D19: =HYPERLINK('Link Config'!$B$2&"plugins/vc/alludium/documents/shared/template-use-guidance.md","Template Use Guidance (vc.document.template_use_guidance)") | E19: operating_guidance
A20: Deal Pipeline | B20: Screening | C20: =HYPERLINK('Link Config'!$B$2&"plugins/vc/tasks/run-investment-screen.md","Run Investment Fit Screen") | D20: =HYPERLINK('Link Config'!$B$2&"plugins/vc/alludium/documents/shared/investment-screening-framework.md","Investment Screening Framework (vc.document.investment_screening_framework)") | E20: methodology | F20: investment_screen_scorecard_artifact_id
A21: Deal Pipeline | B21: Screening | C21: =HYPERLINK('Link Config'!$B$2&"plugins/vc/tasks/run-investment-screen.md","Run Investment Fit Screen") | D21: =HYPERLINK('Link Config'!$B$2&"plugins/vc/alludium/documents/shared/evidence-citation-style-guide.md","Evidence And Citation Style Guide (vc.document.evidence_citation_style_guide)") | E21: style_guide
A22: Deal Pipeline | B22: Screening | C22: =HYPERLINK('Link Config'!$B$2&"plugins/vc/tasks/run-investment-screen.md","Run Investment Fit Screen") | D22: =HYPERLINK('Link Config'!$B$2&"plugins/vc/alludium/documents/shared/template-use-guidance.md","Template Use Guidance (vc.document.template_use_guidance)") | E22: operating_guidance
A23: Deal Pipeline | B23: Evaluation | C23: =HYPERLINK('Link Config'!$B$2&"plugins/vc/tasks/run-follow-up-evaluation.md","Run Opportunity Evaluation") | D23: =HYPERLINK('Link Config'!$B$2&"plugins/vc/alludium/documents/deal-room/follow-up-evaluation-template.md","Opportunity Evaluation Template (vc.document.follow_up_evaluation_template)") | E23: output_template | F23: follow_up_evaluation_artifact_id
A24: Deal Pipeline | B24: Evaluation | C24: =HYPERLINK('Link Config'!$B$2&"plugins/vc/tasks/run-follow-up-evaluation.md","Run Opportunity Evaluation") | D24: =HYPERLINK('Link Config'!$B$2&"plugins/vc/alludium/documents/shared/opportunity-evaluation-framework.md","Opportunity Evaluation Framework (vc.document.opportunity_evaluation_framework)") | E24: methodology
A25: Deal Pipeline | B25: Evaluation | C25: =HYPERLINK('Link Config'!$B$2&"plugins/vc/tasks/run-follow-up-evaluation.md","Run Opportunity Evaluation") | D25: =HYPERLINK('Link Config'!$B$2&"plugins/vc/alludium/documents/shared/evaluation-workstream-guide.md","Evaluation Workstream Guide (vc.document.evaluation_workstream_guide)") | E25: methodology
A26: Deal Pipeline | B26: Evaluation | C26: =HYPERLINK('Link Config'!$B$2&"plugins/vc/tasks/run-follow-up-evaluation.md","Run Opportunity Evaluation") | D26: =HYPERLINK('Link Config'!$B$2&"plugins/vc/alludium/documents/deal-room/commercial-evaluation-guide.md","Commercial Evaluation Guide (vc.document.commercial_evaluation_guide)") | E26: methodology
A27: Deal Pipeline | B27: Evaluation | C27: =HYPERLINK('Link Config'!$B$2&"plugins/vc/tasks/run-follow-up-evaluation.md","Run Opportunity Evaluation") | D27: =HYPERLINK('Link Config'!$B$2&"plugins/vc/alludium/documents/deal-room/technical-evaluation-guide.md","Technical Evaluation Guide (vc.document.technical_evaluation_guide)") | E27: methodology
A28: Deal Pipeline | B28: Evaluation | C28: =HYPERLINK('Link Config'!$B$2&"plugins/vc/tasks/run-follow-up-evaluation.md","Run Opportunity Evaluation") | D28: =HYPERLINK('Link Config'!$B$2&"plugins/vc/alludium/documents/deal-room/financial-evaluation-guide.md","Financial Evaluation Guide (vc.document.financial_evaluation_guide)") | E28: methodology
A29: Deal Pipeline | B29: Evaluation | C29: =HYPERLINK('Link Config'!$B$2&"plugins/vc/tasks/run-follow-up-evaluation.md","Run Opportunity Evaluation") | D29: =HYPERLINK('Link Config'!$B$2&"plugins/vc/alludium/documents/shared/evidence-citation-style-guide.md","Evidence And Citation Style Guide (vc.document.evidence_citation_style_guide)") | E29: style_guide
A30: Deal Pipeline | B30: Evaluation | C30: =HYPERLINK('Link Config'!$B$2&"plugins/vc/tasks/run-follow-up-evaluation.md","Run Opportunity Evaluation") | D30: =HYPERLINK('Link Config'!$B$2&"plugins/vc/alludium/documents/shared/template-use-guidance.md","Template Use Guidance (vc.document.template_use_guidance)") | E30: operating_guidance
A31: Deal Pipeline | B31: Evaluation | C31: =HYPERLINK('Link Config'!$B$2&"plugins/vc/tasks/run-commercial-evaluation.md","Run Commercial Evaluation") | D31: =HYPERLINK('Link Config'!$B$2&"plugins/vc/alludium/documents/deal-room/commercial-evaluation-template.md","Commercial Evaluation Template (vc.document.commercial_evaluation_template)") | E31: output_template | F31: commercial_evaluation_artifact_id
A32: Deal Pipeline | B32: Evaluation | C32: =HYPERLINK('Link Config'!$B$2&"plugins/vc/tasks/run-commercial-evaluation.md","Run Commercial Evaluation") | D32: =HYPERLINK('Link Config'!$B$2&"plugins/vc/alludium/documents/shared/evaluation-workstream-guide.md","Evaluation Workstream Guide (vc.document.evaluation_workstream_guide)") | E32: methodology
A33: Deal Pipeline | B33: Evaluation | C33: =HYPERLINK('Link Config'!$B$2&"plugins/vc/tasks/run-commercial-evaluation.md","Run Commercial Evaluation") | D33: =HYPERLINK('Link Config'!$B$2&"plugins/vc/alludium/documents/deal-room/commercial-evaluation-guide.md","Commercial Evaluation Guide (vc.document.commercial_evaluation_guide)") | E33: methodology
A34: Deal Pipeline | B34: Evaluation | C34: =HYPERLINK('Link Config'!$B$2&"plugins/vc/tasks/run-commercial-evaluation.md","Run Commercial Evaluation") | D34: =HYPERLINK('Link Config'!$B$2&"plugins/vc/alludium/documents/shared/opportunity-evaluation-framework.md","Opportunity Evaluation Framework (vc.document.opportunity_evaluation_framework)") | E34: methodology
A35: Deal Pipeline | B35: Evaluation | C35: =HYPERLINK('Link Config'!$B$2&"plugins/vc/tasks/run-commercial-evaluation.md","Run Commercial Evaluation") | D35: =HYPERLINK('Link Config'!$B$2&"plugins/vc/alludium/documents/shared/evidence-citation-style-guide.md","Evidence And Citation Style Guide (vc.document.evidence_citation_style_guide)") | E35: style_guide
A36: Deal Pipeline | B36: Evaluation | C36: =HYPERLINK('Link Config'!$B$2&"plugins/vc/tasks/run-commercial-evaluation.md","Run Commercial Evaluation") | D36: =HYPERLINK('Link Config'!$B$2&"plugins/vc/alludium/documents/shared/template-use-guidance.md","Template Use Guidance (vc.document.template_use_guidance)") | E36: operating_guidance
A37: Deal Pipeline | B37: Evaluation | C37: =HYPERLINK('Link Config'!$B$2&"plugins/vc/tasks/run-technical-evaluation.md","Run Technical Evaluation") | D37: =HYPERLINK('Link Config'!$B$2&"plugins/vc/alludium/documents/deal-room/technical-evaluation-template.md","Technical Evaluation Template (vc.document.technical_evaluation_template)") | E37: output_template | F37: technical_evaluation_artifact_id
A38: Deal Pipeline | B38: Evaluation | C38: =HYPERLINK('Link Config'!$B$2&"plugins/vc/tasks/run-technical-evaluation.md","Run Technical Evaluation") | D38: =HYPERLINK('Link Config'!$B$2&"plugins/vc/alludium/documents/shared/evaluation-workstream-guide.md","Evaluation Workstream Guide (vc.document.evaluation_workstream_guide)") | E38: methodology
A39: Deal Pipeline | B39: Evaluation | C39: =HYPERLINK('Link Config'!$B$2&"plugins/vc/tasks/run-technical-evaluation.md","Run Technical Evaluation") | D39: =HYPERLINK('Link Config'!$B$2&"plugins/vc/alludium/documents/deal-room/technical-evaluation-guide.md","Technical Evaluation Guide (vc.document.technical_evaluation_guide)") | E39: methodology
A40: Deal Pipeline | B40: Evaluation | C40: =HYPERLINK('Link Config'!$B$2&"plugins/vc/tasks/run-technical-evaluation.md","Run Technical Evaluation") | D40: =HYPERLINK('Link Config'!$B$2&"plugins/vc/alludium/documents/shared/opportunity-evaluation-framework.md","Opportunity Evaluation Framework (vc.document.opportunity_evaluation_framework)") | E40: methodology
A41: Deal Pipeline | B41: Evaluation | C41: =HYPERLINK('Link Config'!$B$2&"plugins/vc/tasks/run-technical-evaluation.md","Run Technical Evaluation") | D41: =HYPERLINK('Link Config'!$B$2&"plugins/vc/alludium/documents/shared/evidence-citation-style-guide.md","Evidence And Citation Style Guide (vc.document.evidence_citation_style_guide)") | E41: style_guide
A42: Deal Pipeline | B42: Evaluation | C42: =HYPERLINK('Link Config'!$B$2&"plugins/vc/tasks/run-technical-evaluation.md","Run Technical Evaluation") | D42: =HYPERLINK('Link Config'!$B$2&"plugins/vc/alludium/documents/shared/template-use-guidance.md","Template Use Guidance (vc.document.template_use_guidance)") | E42: operating_guidance
A43: Deal Pipeline | B43: Evaluation | C43: =HYPERLINK('Link Config'!$B$2&"plugins/vc/tasks/run-financial-evaluation.md","Run Financial Evaluation") | D43: =HYPERLINK('Link Config'!$B$2&"plugins/vc/alludium/documents/deal-room/financial-evaluation-template.md","Financial Evaluation Template (vc.document.financial_evaluation_template)") | E43: output_template | F43: financial_evaluation_artifact_id
A44: Deal Pipeline | B44: Evaluation | C44: =HYPERLINK('Link Config'!$B$2&"plugins/vc/tasks/run-financial-evaluation.md","Run Financial Evaluation") | D44: =HYPERLINK('Link Config'!$B$2&"plugins/vc/alludium/documents/shared/evaluation-workstream-guide.md","Evaluation Workstream Guide (vc.document.evaluation_workstream_guide)") | E44: methodology
A45: Deal Pipeline | B45: Evaluation | C45: =HYPERLINK('Link Config'!$B$2&"plugins/vc/tasks/run-financial-evaluation.md","Run Financial Evaluation") | D45: =HYPERLINK('Link Config'!$B$2&"plugins/vc/alludium/documents/deal-room/financial-evaluation-guide.md","Financial Evaluation Guide (vc.document.financial_evaluation_guide)") | E45: methodology
A46: Deal Pipeline | B46: Evaluation | C46: =HYPERLINK('Link Config'!$B$2&"plugins/vc/tasks/run-financial-evaluation.md","Run Financial Evaluation") | D46: =HYPERLINK('Link Config'!$B$2&"plugins/vc/alludium/documents/shared/opportunity-evaluation-framework.md","Opportunity Evaluation Framework (vc.document.opportunity_evaluation_framework)") | E46: methodology
A47: Deal Pipeline | B47: Evaluation | C47: =HYPERLINK('Link Config'!$B$2&"plugins/vc/tasks/run-financial-evaluation.md","Run Financial Evaluation") | D47: =HYPERLINK('Link Config'!$B$2&"plugins/vc/alludium/documents/shared/evidence-citation-style-guide.md","Evidence And Citation Style Guide (vc.document.evidence_citation_style_guide)") | E47: style_guide
A48: Deal Pipeline | B48: Evaluation | C48: =HYPERLINK('Link Config'!$B$2&"plugins/vc/tasks/run-financial-evaluation.md","Run Financial Evaluation") | D48: =HYPERLINK('Link Config'!$B$2&"plugins/vc/alludium/documents/shared/template-use-guidance.md","Template Use Guidance (vc.document.template_use_guidance)") | E48: operating_guidance
A49: Deal Pipeline | B49: Evaluation | C49: =HYPERLINK('Link Config'!$B$2&"plugins/vc/tasks/run-team-evaluation.md","Run Team Evaluation") | D49: =HYPERLINK('Link Config'!$B$2&"plugins/vc/alludium/documents/deal-room/team-evaluation-template.md","Team Evaluation Template (vc.document.team_evaluation_template)") | E49: output_template | F49: team_evaluation_artifact_id
A50: Deal Pipeline | B50: Evaluation | C50: =HYPERLINK('Link Config'!$B$2&"plugins/vc/tasks/run-team-evaluation.md","Run Team Evaluation") | D50: =HYPERLINK('Link Config'!$B$2&"plugins/vc/alludium/documents/shared/evaluation-workstream-guide.md","Evaluation Workstream Guide (vc.document.evaluation_workstream_guide)") | E50: methodology
A51: Deal Pipeline | B51: Evaluation | C51: =HYPERLINK('Link Config'!$B$2&"plugins/vc/tasks/run-team-evaluation.md","Run Team Evaluation") | D51: =HYPERLINK('Link Config'!$B$2&"plugins/vc/alludium/documents/shared/opportunity-evaluation-framework.md","Opportunity Evaluation Framework (vc.document.opportunity_evaluation_framework)") | E51: methodology
A52: Deal Pipeline | B52: Evaluation | C52: =HYPERLINK('Link Config'!$B$2&"plugins/vc/tasks/run-team-evaluation.md","Run Team Evaluation") | D52: =HYPERLINK('Link Config'!$B$2&"plugins/vc/alludium/documents/shared/evidence-citation-style-guide.md","Evidence And Citation Style Guide (vc.document.evidence_citation_style_guide)") | E52: style_guide
A53: Deal Pipeline | B53: Evaluation | C53: =HYPERLINK('Link Config'!$B$2&"plugins/vc/tasks/run-team-evaluation.md","Run Team Evaluation") | D53: =HYPERLINK('Link Config'!$B$2&"plugins/vc/alludium/documents/shared/template-use-guidance.md","Template Use Guidance (vc.document.template_use_guidance)") | E53: operating_guidance
A54: Deal Pipeline | B54: Evaluation | C54: =HYPERLINK('Link Config'!$B$2&"plugins/vc/tasks/generate-diligence-questions.md","Generate Diligence Questions") | D54: =HYPERLINK('Link Config'!$B$2&"plugins/vc/alludium/documents/shared/investment-diligence-question-framework.md","Investment Diligence Question Framework (vc.document.investment_diligence_question_framework)") | E54: methodology | F54: diligence_question_bank_artifact_id
A55: Deal Pipeline | B55: Evaluation | C55: =HYPERLINK('Link Config'!$B$2&"plugins/vc/tasks/generate-diligence-questions.md","Generate Diligence Questions") | D55: =HYPERLINK('Link Config'!$B$2&"plugins/vc/alludium/documents/shared/opportunity-evaluation-framework.md","Opportunity Evaluation Framework (vc.document.opportunity_evaluation_framework)") | E55: methodology
A56: Deal Pipeline | B56: Evaluation | C56: =HYPERLINK('Link Config'!$B$2&"plugins/vc/tasks/generate-diligence-questions.md","Generate Diligence Questions") | D56: =HYPERLINK('Link Config'!$B$2&"plugins/vc/alludium/documents/shared/evaluation-workstream-guide.md","Evaluation Workstream Guide (vc.document.evaluation_workstream_guide)") | E56: methodology
A57: Deal Pipeline | B57: Evaluation | C57: =HYPERLINK('Link Config'!$B$2&"plugins/vc/tasks/generate-diligence-questions.md","Generate Diligence Questions") | D57: =HYPERLINK('Link Config'!$B$2&"plugins/vc/alludium/documents/deal-room/commercial-evaluation-guide.md","Commercial Evaluation Guide (vc.document.commercial_evaluation_guide)") | E57: methodology
A58: Deal Pipeline | B58: Evaluation | C58: =HYPERLINK('Link Config'!$B$2&"plugins/vc/tasks/generate-diligence-questions.md","Generate Diligence Questions") | D58: =HYPERLINK('Link Config'!$B$2&"plugins/vc/alludium/documents/deal-room/technical-evaluation-guide.md","Technical Evaluation Guide (vc.document.technical_evaluation_guide)") | E58: methodology
A59: Deal Pipeline | B59: Evaluation | C59: =HYPERLINK('Link Config'!$B$2&"plugins/vc/tasks/generate-diligence-questions.md","Generate Diligence Questions") | D59: =HYPERLINK('Link Config'!$B$2&"plugins/vc/alludium/documents/deal-room/financial-evaluation-guide.md","Financial Evaluation Guide (vc.document.financial_evaluation_guide)") | E59: methodology
A60: Deal Pipeline | B60: Evaluation | C60: =HYPERLINK('Link Config'!$B$2&"plugins/vc/tasks/generate-diligence-questions.md","Generate Diligence Questions") | D60: =HYPERLINK('Link Config'!$B$2&"plugins/vc/alludium/documents/deal-room/formal-diligence-workstream-guide.md","Formal Diligence Workstream Guide (vc.document.formal_diligence_workstream_guide)") | E60: methodology
A61: Deal Pipeline | B61: Evaluation | C61: =HYPERLINK('Link Config'!$B$2&"plugins/vc/tasks/generate-diligence-questions.md","Generate Diligence Questions") | D61: =HYPERLINK('Link Config'!$B$2&"plugins/vc/alludium/documents/deal-room/formal-diligence-checklist.md","Formal Diligence Checklist (vc.document.formal_diligence_checklist)") | E61: checklist
A62: Deal Pipeline | B62: Evaluation | C62: =HYPERLINK('Link Config'!$B$2&"plugins/vc/tasks/generate-diligence-questions.md","Generate Diligence Questions") | D62: =HYPERLINK('Link Config'!$B$2&"plugins/vc/alludium/documents/deal-room/legal-diligence-guide.md","Legal Diligence Guide (vc.document.legal_diligence_guide)") | E62: methodology
A63: Deal Pipeline | B63: Evaluation | C63: =HYPERLINK('Link Config'!$B$2&"plugins/vc/tasks/generate-diligence-questions.md","Generate Diligence Questions") | D63: =HYPERLINK('Link Config'!$B$2&"plugins/vc/alludium/documents/shared/evidence-citation-style-guide.md","Evidence And Citation Style Guide (vc.document.evidence_citation_style_guide)") | E63: style_guide
A64: Deal Pipeline | B64: Evaluation | C64: =HYPERLINK('Link Config'!$B$2&"plugins/vc/tasks/generate-diligence-questions.md","Generate Diligence Questions") | D64: =HYPERLINK('Link Config'!$B$2&"plugins/vc/alludium/documents/shared/template-use-guidance.md","Template Use Guidance (vc.document.template_use_guidance)") | E64: operating_guidance
A65: Deal Pipeline | B65: Decision Review | C65: =HYPERLINK('Link Config'!$B$2&"plugins/vc/tasks/prepare-team-review-pack.md","Prepare Team Review Pack") | D65: =HYPERLINK('Link Config'!$B$2&"plugins/vc/alludium/documents/deal-room/review-pack-checklist.md","Review Pack Checklist (vc.document.review_pack_checklist)") | E65: output_template | F65: team_review_pack_artifact_id
A66: Deal Pipeline | B66: Decision Review | C66: =HYPERLINK('Link Config'!$B$2&"plugins/vc/tasks/prepare-team-review-pack.md","Prepare Team Review Pack") | D66: =HYPERLINK('Link Config'!$B$2&"plugins/vc/alludium/documents/shared/opportunity-evaluation-framework.md","Opportunity Evaluation Framework (vc.document.opportunity_evaluation_framework)") | E66: methodology
A67: Deal Pipeline | B67: Decision Review | C67: =HYPERLINK('Link Config'!$B$2&"plugins/vc/tasks/prepare-team-review-pack.md","Prepare Team Review Pack") | D67: =HYPERLINK('Link Config'!$B$2&"plugins/vc/alludium/documents/shared/evaluation-workstream-guide.md","Evaluation Workstream Guide (vc.document.evaluation_workstream_guide)") | E67: methodology
A68: Deal Pipeline | B68: Decision Review | C68: =HYPERLINK('Link Config'!$B$2&"plugins/vc/tasks/prepare-team-review-pack.md","Prepare Team Review Pack") | D68: =HYPERLINK('Link Config'!$B$2&"plugins/vc/alludium/documents/deal-room/formal-diligence-workstream-guide.md","Formal Diligence Workstream Guide (vc.document.formal_diligence_workstream_guide)") | E68: methodology
A69: Deal Pipeline | B69: Decision Review | C69: =HYPERLINK('Link Config'!$B$2&"plugins/vc/tasks/prepare-team-review-pack.md","Prepare Team Review Pack") | D69: =HYPERLINK('Link Config'!$B$2&"plugins/vc/alludium/documents/deal-room/formal-diligence-checklist.md","Formal Diligence Checklist (vc.document.formal_diligence_checklist)") | E69: checklist
A70: Deal Pipeline | B70: Decision Review | C70: =HYPERLINK('Link Config'!$B$2&"plugins/vc/tasks/prepare-team-review-pack.md","Prepare Team Review Pack") | D70: =HYPERLINK('Link Config'!$B$2&"plugins/vc/alludium/documents/shared/evidence-citation-style-guide.md","Evidence And Citation Style Guide (vc.document.evidence_citation_style_guide)") | E70: style_guide
A71: Deal Pipeline | B71: Decision Review | C71: =HYPERLINK('Link Config'!$B$2&"plugins/vc/tasks/prepare-team-review-pack.md","Prepare Team Review Pack") | D71: =HYPERLINK('Link Config'!$B$2&"plugins/vc/alludium/documents/shared/template-use-guidance.md","Template Use Guidance (vc.document.template_use_guidance)") | E71: operating_guidance
A72: Deal Pipeline | B72: Decision Review | C72: =HYPERLINK('Link Config'!$B$2&"plugins/vc/tasks/prepare-partner-review-pack.md","Prepare Partner Review Pack") | D72: =HYPERLINK('Link Config'!$B$2&"plugins/vc/alludium/documents/deal-room/review-pack-checklist.md","Review Pack Checklist (vc.document.review_pack_checklist)") | E72: output_template | F72: partner_review_pack_artifact_id
A73: Deal Pipeline | B73: Decision Review | C73: =HYPERLINK('Link Config'!$B$2&"plugins/vc/tasks/prepare-partner-review-pack.md","Prepare Partner Review Pack") | D73: =HYPERLINK('Link Config'!$B$2&"plugins/vc/alludium/documents/shared/opportunity-evaluation-framework.md","Opportunity Evaluation Framework (vc.document.opportunity_evaluation_framework)") | E73: methodology
A74: Deal Pipeline | B74: Decision Review | C74: =HYPERLINK('Link Config'!$B$2&"plugins/vc/tasks/prepare-partner-review-pack.md","Prepare Partner Review Pack") | D74: =HYPERLINK('Link Config'!$B$2&"plugins/vc/alludium/documents/shared/evaluation-workstream-guide.md","Evaluation Workstream Guide (vc.document.evaluation_workstream_guide)") | E74: methodology
A75: Deal Pipeline | B75: Decision Review | C75: =HYPERLINK('Link Config'!$B$2&"plugins/vc/tasks/prepare-partner-review-pack.md","Prepare Partner Review Pack") | D75: =HYPERLINK('Link Config'!$B$2&"plugins/vc/alludium/documents/deal-room/formal-diligence-workstream-guide.md","Formal Diligence Workstream Guide (vc.document.formal_diligence_workstream_guide)") | E75: methodology
A76: Deal Pipeline | B76: Decision Review | C76: =HYPERLINK('Link Config'!$B$2&"plugins/vc/tasks/prepare-partner-review-pack.md","Prepare Partner Review Pack") | D76: =HYPERLINK('Link Config'!$B$2&"plugins/vc/alludium/documents/deal-room/formal-diligence-checklist.md","Formal Diligence Checklist (vc.document.formal_diligence_checklist)") | E76: checklist
A77: Deal Pipeline | B77: Decision Review | C77: =HYPERLINK('Link Config'!$B$2&"plugins/vc/tasks/prepare-partner-review-pack.md","Prepare Partner Review Pack") | D77: =HYPERLINK('Link Config'!$B$2&"plugins/vc/alludium/documents/shared/evidence-citation-style-guide.md","Evidence And Citation Style Guide (vc.document.evidence_citation_style_guide)") | E77: style_guide
A78: Deal Pipeline | B78: Decision Review | C78: =HYPERLINK('Link Config'!$B$2&"plugins/vc/tasks/prepare-partner-review-pack.md","Prepare Partner Review Pack") | D78: =HYPERLINK('Link Config'!$B$2&"plugins/vc/alludium/documents/shared/template-use-guidance.md","Template Use Guidance (vc.document.template_use_guidance)") | E78: operating_guidance
A79: Deal Pipeline | B79: Decision Review | C79: =HYPERLINK('Link Config'!$B$2&"plugins/vc/tasks/create-ic-memo.md","Create IC Memo") | D79: =HYPERLINK('Link Config'!$B$2&"plugins/vc/alludium/documents/deal-room/investment-memo-template.md","Investment Memo Template (vc.document.investment_memo_template)") | E79: output_template | F79: investment_memo_artifact_id
A80: Deal Pipeline | B80: Decision Review | C80: =HYPERLINK('Link Config'!$B$2&"plugins/vc/tasks/create-ic-memo.md","Create IC Memo") | D80: =HYPERLINK('Link Config'!$B$2&"plugins/vc/alludium/documents/shared/opportunity-evaluation-framework.md","Opportunity Evaluation Framework (vc.document.opportunity_evaluation_framework)") | E80: methodology
A81: Deal Pipeline | B81: Decision Review | C81: =HYPERLINK('Link Config'!$B$2&"plugins/vc/tasks/create-ic-memo.md","Create IC Memo") | D81: =HYPERLINK('Link Config'!$B$2&"plugins/vc/alludium/documents/shared/evaluation-workstream-guide.md","Evaluation Workstream Guide (vc.document.evaluation_workstream_guide)") | E81: methodology
A82: Deal Pipeline | B82: Decision Review | C82: =HYPERLINK('Link Config'!$B$2&"plugins/vc/tasks/create-ic-memo.md","Create IC Memo") | D82: =HYPERLINK('Link Config'!$B$2&"plugins/vc/alludium/documents/deal-room/formal-diligence-workstream-guide.md","Formal Diligence Workstream Guide (vc.document.formal_diligence_workstream_guide)") | E82: methodology
A83: Deal Pipeline | B83: Decision Review | C83: =HYPERLINK('Link Config'!$B$2&"plugins/vc/tasks/create-ic-memo.md","Create IC Memo") | D83: =HYPERLINK('Link Config'!$B$2&"plugins/vc/alludium/documents/deal-room/formal-diligence-checklist.md","Formal Diligence Checklist (vc.document.formal_diligence_checklist)") | E83: checklist
A84: Deal Pipeline | B84: Decision Review | C84: =HYPERLINK('Link Config'!$B$2&"plugins/vc/tasks/create-ic-memo.md","Create IC Memo") | D84: =HYPERLINK('Link Config'!$B$2&"plugins/vc/alludium/documents/shared/evidence-citation-style-guide.md","Evidence And Citation Style Guide (vc.document.evidence_citation_style_guide)") | E84: style_guide
A85: Deal Pipeline | B85: Decision Review | C85: =HYPERLINK('Link Config'!$B$2&"plugins/vc/tasks/create-ic-memo.md","Create IC Memo") | D85: =HYPERLINK('Link Config'!$B$2&"plugins/vc/alludium/documents/shared/template-use-guidance.md","Template Use Guidance (vc.document.template_use_guidance)") | E85: operating_guidance
A86: Deal Pipeline | B86: Decision Review | C86: =HYPERLINK('Link Config'!$B$2&"plugins/vc/tasks/prepare-ic-agenda.md","Prepare IC Agenda") | D86: =HYPERLINK('Link Config'!$B$2&"plugins/vc/alludium/documents/deal-room/ic-agenda-template.md","IC Agenda Template (vc.document.ic_agenda_template)") | E86: output_template | F86: ic_agenda_artifact_id
A87: Deal Pipeline | B87: Decision Review | C87: =HYPERLINK('Link Config'!$B$2&"plugins/vc/tasks/prepare-ic-agenda.md","Prepare IC Agenda") | D87: =HYPERLINK('Link Config'!$B$2&"plugins/vc/alludium/documents/shared/template-use-guidance.md","Template Use Guidance (vc.document.template_use_guidance)") | E87: operating_guidance
A88: Deal Pipeline | B88: Decision Review | C88: =HYPERLINK('Link Config'!$B$2&"plugins/vc/tasks/review-ic-memo.md","Review IC Memo") | D88: =HYPERLINK('Link Config'!$B$2&"plugins/vc/alludium/documents/deal-room/ic-memo-review-template.md","IC Memo Review Template (vc.document.ic_memo_review_template)") | E88: output_template | F88: ic_memo_review_artifact_id
A89: Deal Pipeline | B89: Decision Review | C89: =HYPERLINK('Link Config'!$B$2&"plugins/vc/tasks/review-ic-memo.md","Review IC Memo") | D89: =HYPERLINK('Link Config'!$B$2&"plugins/vc/alludium/documents/shared/opportunity-evaluation-framework.md","Opportunity Evaluation Framework (vc.document.opportunity_evaluation_framework)") | E89: methodology
A90: Deal Pipeline | B90: Decision Review | C90: =HYPERLINK('Link Config'!$B$2&"plugins/vc/tasks/review-ic-memo.md","Review IC Memo") | D90: =HYPERLINK('Link Config'!$B$2&"plugins/vc/alludium/documents/shared/evaluation-workstream-guide.md","Evaluation Workstream Guide (vc.document.evaluation_workstream_guide)") | E90: methodology
A91: Deal Pipeline | B91: Decision Review | C91: =HYPERLINK('Link Config'!$B$2&"plugins/vc/tasks/review-ic-memo.md","Review IC Memo") | D91: =HYPERLINK('Link Config'!$B$2&"plugins/vc/alludium/documents/deal-room/formal-diligence-workstream-guide.md","Formal Diligence Workstream Guide (vc.document.formal_diligence_workstream_guide)") | E91: methodology
A92: Deal Pipeline | B92: Decision Review | C92: =HYPERLINK('Link Config'!$B$2&"plugins/vc/tasks/review-ic-memo.md","Review IC Memo") | D92: =HYPERLINK('Link Config'!$B$2&"plugins/vc/alludium/documents/deal-room/formal-diligence-checklist.md","Formal Diligence Checklist (vc.document.formal_diligence_checklist)") | E92: checklist
A93: Deal Pipeline | B93: Decision Review | C93: =HYPERLINK('Link Config'!$B$2&"plugins/vc/tasks/review-ic-memo.md","Review IC Memo") | D93: =HYPERLINK('Link Config'!$B$2&"plugins/vc/alludium/documents/shared/evidence-citation-style-guide.md","Evidence And Citation Style Guide (vc.document.evidence_citation_style_guide)") | E93: style_guide
A94: Deal Pipeline | B94: Decision Review | C94: =HYPERLINK('Link Config'!$B$2&"plugins/vc/tasks/review-ic-memo.md","Review IC Memo") | D94: =HYPERLINK('Link Config'!$B$2&"plugins/vc/alludium/documents/shared/template-use-guidance.md","Template Use Guidance (vc.document.template_use_guidance)") | E94: operating_guidance
A95: Deal Pipeline | B95: Decision Review | C95: =HYPERLINK('Link Config'!$B$2&"plugins/vc/tasks/record-ic-decision.md","Record IC Decision") | D95: =HYPERLINK('Link Config'!$B$2&"plugins/vc/alludium/documents/deal-room/ic-decision-record-template.md","IC Decision Record Template (vc.document.ic_decision_record_template)") | E95: output_template | F95: ic_decision_record_artifact_id
A96: Deal Pipeline | B96: Decision Review | C96: =HYPERLINK('Link Config'!$B$2&"plugins/vc/tasks/record-ic-decision.md","Record IC Decision") | D96: =HYPERLINK('Link Config'!$B$2&"plugins/vc/alludium/documents/shared/evidence-citation-style-guide.md","Evidence And Citation Style Guide (vc.document.evidence_citation_style_guide)") | E96: style_guide
A97: Deal Pipeline | B97: Decision Review | C97: =HYPERLINK('Link Config'!$B$2&"plugins/vc/tasks/record-ic-decision.md","Record IC Decision") | D97: =HYPERLINK('Link Config'!$B$2&"plugins/vc/alludium/documents/shared/template-use-guidance.md","Template Use Guidance (vc.document.template_use_guidance)") | E97: operating_guidance
A98: Deal Pipeline | B98: Deal Structuring | C98: =HYPERLINK('Link Config'!$B$2&"plugins/vc/tasks/analyze-deal-terms.md","Analyze Deal Terms") | D98: =HYPERLINK('Link Config'!$B$2&"plugins/vc/alludium/documents/deal-room/deal-terms-analysis-template.md","Deal Terms Analysis Template (vc.document.deal_terms_analysis_template)") | E98: output_template | F98: deal_terms_analysis_artifact_id
A99: Deal Pipeline | B99: Deal Structuring | C99: =HYPERLINK('Link Config'!$B$2&"plugins/vc/tasks/analyze-deal-terms.md","Analyze Deal Terms") | D99: =HYPERLINK('Link Config'!$B$2&"plugins/vc/alludium/documents/shared/evidence-citation-style-guide.md","Evidence And Citation Style Guide (vc.document.evidence_citation_style_guide)") | E99: style_guide
A100: Deal Pipeline | B100: Deal Structuring | C100: =HYPERLINK('Link Config'!$B$2&"plugins/vc/tasks/analyze-deal-terms.md","Analyze Deal Terms") | D100: =HYPERLINK('Link Config'!$B$2&"plugins/vc/alludium/documents/shared/template-use-guidance.md","Template Use Guidance (vc.document.template_use_guidance)") | E100: operating_guidance
...

Sheet Link Config
A1: Variable | B1: Value | C1: Notes
A2: GITHUB_BASE_URL | B2: https://github.com/alludium/alludium-packs/blob/codex/vc-blueprint-refactor/ | C2: Update this after merge, for example to https://github.com/alludium/alludium-packs/blob/main/
